Workbook

Sheet Overview
A1: PEMS - Platform Overview
A3: Read this sheet first, before Read Me / Instructions / Backlog, in any new session. It is the fastest orientation to what PEMS is, where it is going and how work is done here. Update it whenever something it describes goes stale (not only Instructions/Memory).
A5: What PEMS is
A6: PEMS is an enterprise .NET system (ASP.NET Core MVC/Razor + EF Core 10 + SQL Server) for engineering and maintenance management in the oil and petrochemical industry: EDMS/VDR, CMMS/EAM, permit to work (PTW), inventory, production, reliability and local AI (Ollama/OCR). Today it is a set of fixed modules (98 controllers, 91 View folders, 116 migrations, 1,403 tests). PEMS is a brand-new product whose long-term aim is to become the single platform for its customers' engineering and maintenance processes.
A8: New direction: from fixed software to a dynamic BPMS
A9: Forms, modules and workflows must be fully creatable and editable by authorized users, with no coding and no build/deploy. Today's fixed modules are progressively converted into metadata definitions (strangler pattern, backlog area MIG) and specialized parts (AI, OCR, EDMS revision engine, reliability) stay as Domain Packs with extension points. Shared engines: metadata registry, form, workflow, rules, access/RLS, events, reporting.
A11: Commercial model
A12: For now, an on-prem licence locked to the machine and the install time: even if a whole machine is imaged and deployed elsewhere it must not work. Process: a request file from the customer server, returned to the vendor, a signed licence file issued, installed. Licence types: lifetime, term (a time period), trial, demo. Details in the Licensing Design sheet and the LIC area. The product never calls out (production has no internet); the website and the demo are the only online parts.
A14: Prioritization rule of this backlog
A15: Priority is set by 'ability to sell' and 'dynamic core': P0 = without it nothing can be sold or the dynamic platform cannot form (foundation decisions, metadata, grid/form, licensing, RLS, demo, install); P1 = needed for commercial release 1.0; P2 = competitive/next stage; P3 = later. The legacy domain backlog (CMMS/EDMS etc.) matters but stays behind sales and dynamicization work unless it blocks them.
A17: Current state (estimated from code, no build executed)
A18: Strengths: domain breadth, modern authentication (Identity + FIDO2), a central access model, a workflow runtime, local AI. Main gaps: no App/Entity/Form registry and no form builder; no workflow studio; no licensing and no installer; no server-side session registry; no Jalali UI; default culture is en. No build/test has been run (row F_BASE). Database creation, install and update are fully code-first (migrator + Admin Database Update page, 2026-10-22).
... A24: 'Is X done / status of Y?' -> Backlog (Evidence column). 'What is next?' -> Roadmap. 'Which rules always apply?' -> Instructions. 'What do we know from earlier platforms?' -> Lessons. 'Which capabilities must PEMS offer?' -> Capability Checklist. 'How does licensing work?' -> Licensing Design. 'What is supported and up to which limits?' -> Supportability Matrix. 'What happened to an old task?' -> Old to New Map.

Sheet Read Me
A1: PEMS - Backlog & Roadmap (rebuilt edition)
A2: Created 2026-10-15 from the static PEMS audit plus lessons and capabilities of a reference platform. The filename is deliberately date-free and the file is updated in place.
A4: Sheets
A5: Sheet | B5: Purpose
A6: Overview | B6: Orientation - read first.
A7: Read Me | B7: This sheet: column guide, statuses, priorities.
A8: Instructions | B8: Standing rules applied in every task.
A9: Backlog | B9: The unified task list (source of truth).
A10: Test Plan | B10: QA cases for Done rows and for P0 rows after implementation.
A11: Roadmap | B11: Milestones and execution order.
A12: Supportability Matrix | B12: What is supported (capabilities, limits, platforms, versions) - updated in every finished task.
A13: Licensing Design | B13: Machine/install-locked licensing design and threat table.
A14: Capability Checklist | B14: Capabilities PEMS must offer, sourced from the reference platform.
A15: Lessons | B15: Durable lessons and facts (reference platform and PEMS).
A16: Old to New Map | B16: Mapping of every old backlog row to the new rows.
A17: Summary | B17: Automatic counts (formulas) over the Backlog.
A19: Backlog columns
A20: Column | B20: Meaning
A21: # | B21: Permanent number; never reused.
A22: Doer | B22: Claude = doable in a code session; User = decision or legal/commercial/operational work of the owner.
A23: Area | B23: Work area.
A24: Track | B24: Feature, Bug Fix, Tech Debt, Decision Needed, Library Modernization, Research, Docs, Legal/Business, Ops Process.
A25: Status | B25: Not Started, In Progress, Partial, Done, Hold (decided but paused by the PM until released), Later (deliberately deferred, kept in the backlog), Cancelled, Obsolete. Done only with evidence.
A26: Confirmed by PM | B26: Yes when the owner/PM has reviewed and confirmed the row (its scope, priority and milestone); No until then. Only the PM sets this flag; automated updates of this file preserve what the PM entered.
A27: Sprint | B27: Sprint the row is planned in (Sprint 1, Sprint 1 stretch); empty = backlog. The Sprint 1 sheet has goal, capacity and the committed list.
A28: Owner | B28: Accountable person for the row in a sprint (Member A / Member B until names are mapped); the doer may still be the assistant.
A29: Group | B29: Related tasks grouped into one workstream; filter on this column to see and decide a whole group together.
A30: Priority | B30: P0 sales blocker/dynamic core, P1 needed for commercial 1.0, P2 competitive, P3 later.
A31: Evidence | B31: What was seen in code/documents today (or a known pitfall).
... A40: Old Ref | B40: Related row in the old audit (OLD-n) or OLD-Dn for existing capabilities.
A42: Components and versions (bill of materials)
A43: Component | B43: Version / status
A44: PEMS (system) | B44: No official version defined - action: F_CI
A45: PEMS.Web / Application / Domain / Persistence / WorkflowPlatform / AI | B45: .NET 10 SDK, EF Core 10.0.10
A46: Workbook | B46: 1.2 - 2026-10-22 (English edition; lives in the repository at plan/PEMS_Backlog_Roadmap.xlsx)
A48: Priorities
A49: Priority | B49: Definition
A50: P0 | B50: Sales blocker or dynamic core - nothing proceeds without it
A51: P1 | B51: Needed for commercial release 1.0
A52: P2 | B52: Competitive / next stage
A53: P3 | B53: Later or uncertain
A55: Areas
A56: Area | B56: Internal code
A57: Foundation, Architecture Decisions & Baseline | B57: FND
A58: Metadata Core & Dynamic Platform | B58: DYN
A59: Component Library & Design System | B59: CMP
A60: Dynamic Form Builder | B60: FRM
A61: Dynamic Module Builder | B61: MOD
A62: Workflow Studio & BPMS | B62: WFL
A63: Static-to-Dynamic Module Migration | B63: MIG
A64: Licensing & Protection | B64: LIC
A65: Company, Brand & Commercial Packaging | B65: BRD
A66: Online Demo | B66: DEM
A67: Commercial Website | B67: WEB
... A83: Main Host: Landing & Demo Deployment | B83: HST

Sheet Instructions
A1: Standing instructions for the PEMS project
A2: Apply these in every task even when the request does not restate them. Keep in sync with Memory; a rule changes only with the owner's decision.
A4: # | B4: Rule | C4: Description
A5: 1 | B5: Offline execution | C5: Production has no internet: no CDN, external call, telemetry or online licence/update check is allowed in the product. Any new library must run fully offline and not depend on an online source at build time. (The website and demo are online parts and are separate from the product.)
A6: 2 | B6: Library-first, with licence control | C6: Before hand-building (expression engine, grid, workflow designer, rules, scheduler, PDF/Excel) check for a mature library. For commercial sale every library licence (copyleft, revenue thresholds, mandatory watermark) must be recorded in row L_OSS; an unsuitable library is replaced. Custom code only with a stated reason.
A7: 3 | B7: Engines once, not per module | C7: Each shared capability (metadata, forms, workflow, access/RLS, events, reporting, licensing) has exactly one implementation; modules call it. Parallel concepts are forbidden.
A8: 4 | B8: No new static modules | C8: From now on a new module is built first as metadata (form/view/workflow). If that is impossible, record the reason and the needed extension point in an ADR. A new static module without this record is not allowed.
A9: 5 | B9: Persian-first, English file | C9: The product default language is Persian with RTL; displayed dates are Jalali with Gregorian/UTC storage. This workbook, code identifiers and ADRs are written in English.
A10: 6 | B10: Go forward, not backward-compatible | C10: During development applied migrations are not edited; always add a new numbered migration/seed. No backward-compatibility shim unless a live customer needs it.
A11: 7 | B11: Task workflow | C11: Before starting set the row to In Progress; afterwards commit separately with a version bump and CHANGELOG, then update Status/Report in this file as its own commit. Message format 'vX.Y.Z: description'. Never use 'git add -A'; stage only specific files.
A12: 8 | B12: Order of work: scope, plan, design, implement | C12: (a) Everything the user said, including later clarifications; (b) update the backlog row before designing; (c) then design library-first with best practice; (d) then implement.
A13: 9 | B13: Three version numbers | C13: System = CalVer (YYYY.MM.PATCH); components = SemVer; editing this file does not change a version. The component table is on the Read Me sheet.
A14: 10 | B14: Secrets and keys | C14: No real secret, key or connection string in the repo or release package. The licence-signing private key and the reset private key are created and used only on the owner computers (Hamid's and Saber's own) and are never in the repo, on a CI or shared server, or in the assistant's environment (L_KEYS).
A15: 11 | B15: Licence active everywhere | C15: Licence checks apply in all environments (a signed dev licence); no bypass flag may reach any package. Always-free surfaces come only from an allowlist (L_FREE).
A16: 12 | B16: Central RLS | C16: No data path (list, search, report, export, API, AI) is without the central RLS filter; direct role-based checks are not allowed.
... A32: 28 | B32: Study existing tasks before adding one | C32: Owner decision 2026-10-26: before adding a task (backlog row and Jira issue) read the existing ones - search the backlog and Jira by area, files, goal and keywords, including Done and Hold rows. If an existing task covers the work or can absorb it, modify that task (extend What to do / Done when, update the workbook row, the Jira issue and a comment saying what changed and why) instead of adding a new one. Add a new row only when no task fits, and name the tasks that were checked in its Evidence. A new row keeps the next free Plan ID; held (Hold) tasks count as not open.

Sheet Backlog
A1: # | B1: Doer | C1: Area | D1: Task | E1: Track | F1: Status | G1: Priority | H1: Evidence | I1: Prompt | J1: Requirement | K1: Report | L1: Milestone | M1: Effort | N1: Commercial | O1: Depends | P1: Reference (Titan) | Q1: Old Ref | R1: Group | S1: Confirmed by PM | T1: Sprint | U1: Owner
A2: 1 | B2: Claude | C2: Foundation, Architecture Decisions & Baseline | D2: Run the build and test suite once and store a baseline report (counts, duration, environment, every failing test) | E2: Tech Debt | F2: Not Started | G2: P0 | H2: The previous audit was static only; no real build or test run exists. About 1,403 Fact/Theory tests exist but their pass/fail state is unknown. | I2: 1) On a clean checkout run dotnet restore, build and test for PEMS.slnx with a reachable SQL Server (LocalDB or SQL Express) and PEMS_TEST_CONNECTION set. 2) Store the console output and a summary under plan/baseline/ (date, SDK and SQL versions, pass/fail/skip counts, duration). 3) List every failing test with its cause: pre-existing, environment, or real defect. 4) Create one backlog row per real defect. | J2: Done when: plan/baseline/<date>.md exists with the numbers above; each failing test is listed with a cause; each real defect has its own backlog row. Known today (not yet in a report): LinuxDeploymentArtifactsTests LF check, a SQLEXPRESS-only sidebar test and ImportCenterNavigationTests (LetterCompose) fail on a clean main. | L2: M0 | M2: S | N2: High | Q2: OLD-1 | R2: Foundation & decisions | S2: No | T2: Sprint 1 | U2: Member B
A3: 2 | B3: Claude | C3: Foundation, Architecture Decisions & Baseline | D3: Create the architecture decision record (ADR) log in plan/adr and record the decisions already taken | E3: Docs | F3: Not Started | G3: P0 | H3: Key decisions (dynamic storage, UI stack, licensing, libraries) are not written down; they are scattered across Role/ documents. | I3: 1) Add plan/adr/TEMPLATE.md (context, decision, alternatives, consequences, status, date, decided by). 2) Write one ADR each for: hybrid storage (#4), Razor plus a separate PEMS.UI library (#5, docs/design/COMPONENT_LIBRARY_PLAN.md), code-first database (#309), environment and secrets files (#315), licensing threat model and VM policy (#96, #97), demo branch policy (#300). 3) Link each ADR from the backlog row it explains. | J3: Done when: plan/adr contains the template and six ADRs approved by Member A; every backlog row marked decided points to its ADR. | K3: Added plan/adr: TEMPLATE.md, README index and ADR-0001..0006 (hybrid storage, Razor + PEMS.UI, code-first database, env/secrets files, licensing threat model + VM policy, demo/staging branch policy), each linked from its explaining doc. Merged in atapems-tech/PEMS#4. Approved by Member A (Hamid Maleki) 2026-10-27. No Supportability Matrix change. | L3: M0 | M3: S | N3: High | Q3: OLD-2 | R3: Foundation & decisions | S3: No | T3: Sprint 1 | U3: Member A
A4: 3 | B4: Claude | C4: Foundation, Architecture Decisions & Baseline | D4: Write the one-page platform operating model: what is the dynamic engine, what are Domain Packs, what stays static | E4: Docs | F4: Not Started | G4: P0 | H4: Today PEMS is a set of fixed MVC modules (98 controllers, 91 View folders). The boundary between shared engines and domain code is not written down. | I4: 1) Classify every existing capability (the 98 controllers; use docs/design/ui-pattern-audit.csv and the Capability Checklist sheet) as engine, domain pack or permanently static. 2) Define the extension points a pack may use (actions, widgets, validators, views) and what a pack may never change. 3) Draw the layer diagram (engine, packs, UI library, licensing). Output: docs/architecture/PLATFORM_OPERATING_MODEL.md. | J4: Done when: Member A approved the document; every module appears in exactly one class; rows #10, #85 and #94 reference it. | L4: M0 | M4: M | N4: Sales blocker | Q4: OLD-3 | R4: Foundation & decisions | S4: No | T4: Sprint 1 | U4: Member A
A5: 4 | B5: User | C5: Foundation, Architecture Decisions & Baseline | D5: Storage for user-created entities (decided: hybrid - real tables for user-built entities, JSON column for custom fields on existing entities) | E5: Decision Needed | F5: Done | G5: P0 | H5: Options: (a) real SQL tables via guided DDL, (b) JSON column plus indexed computed columns, (c) EAV. PEMS runs on EF Core 10 + SQL Server. | I5: Benchmark all three with a small prototype (100k records, filter/sort/report). Initial recommendation: hybrid, with real tables for fully user-defined entities and a JSON column for custom fields on existing static entities. | J5: An approved ADR with performance criteria, migration cost, reporting impact and effect on RLS and audit. | K5: Decided 2026-10-18: hybrid - real SQL tables for fully user-built entities, one JSON column for custom fields on existing entities. Prototype validation happens in D_DDL/D_SCHEMA; ADR to be written under F_ADR. ADR: plan/adr/0001-hybrid-storage-for-user-built-entities.md | L5: M0 | M5: M | N5: Sales blocker | P5: Titan #17 #61 | R5: Foundation & decisions | S5: Yes
A6: 5 | B6: User | C6: Foundation, Architecture Decisions & Baseline | D6: UI layer for reusable components (decided: Razor plus a reusable component library, designers as embedded JavaScript components) | E6: Decision Needed | F6: Done | G6: P0 | H6: The current UI is Razor + Bootstrap + jQuery with 225 views and page-specific JS/CSS (pems-data-grid.js etc.). Options: ViewComponent/TagHelper + Web Components, Blazor, or an SPA hosted inside the app. | I6: Compare the three options with a vertical slice (grid + form). Criteria: fully offline without CDN, RTL, form-builder velocity, upgrade path from existing Razor. | J6: An approved ADR; all CMP_* and FRM_* work is defined against it. | K6: Decided 2026-10-18: keep Razor and build a reusable component library, with the form/workflow designers as embedded JavaScript components. ADR to be written under F_ADR. 2026-10-23: refined in docs/design/COMPONENT_LIBRARY_PLAN.md - separate Razor Class Library PEMS.UI (decided); canonical technology recommended as descriptor-driven static Razor components with an MVC Tag Helper facade, gated by spike #319 (the vertical-slice comparison this row asked for was never run). ADR: plan/adr/0002-razor-with-separate-pems-ui-library.md (component technology D3 still open, spike #319) ADR-0001..0006 approved by Member A 2026-10-27. Component technology (D3): spike #319 run 2026-10-27, see ADR-0007 (proposed, static Razor components + Tag Helper facade). | L6: M0 | M6: M | N6: Sales blocker | P6: Titan #177 | R6: Foundation & decisions | S6: Yes
A7: 6 | B7: Claude | C7: Foundation, Architecture Decisions & Baseline | D7: Decision and evaluation of libraries (library-first) with license and offline checks | E7: Library Modernization | F7: Not Started | G7: P0 | H7: Building from scratch must be justified. Needs: expression engine (NCalc/DynamicExpresso), grid, workflow designer, rule/policy engine, scheduler. | I7: For each need compare at least two options on commercial license, fully offline operation, active maintenance and RTL support, and record the result. | J7: A library decision table with a column 'license suitable for commercial sale?'; no runtime dependency needs a CDN or internet. | L7: M0 | M7: M | N7: High | P7: Titan #7 #53 #62 | Q7: OLD-87 OLD-92 | R7: Foundation & decisions | S7: No
A8: 7 | B8: Claude | C8: Foundation, Architecture Decisions & Baseline | D8: Make the build workflow fail on red tests and publish a versioned artifact on version tags | E8: Feature | F8: Not Started | G8: P0 | H8: Owner requirement 2026-10-18: the demo is deployed from the demo branch of the product repository and the landing from its own repository. The product repository needs a reusable build-and-test workflow. There is no automated pipeline today; only a Dockerfile and docker-compose exist. | I8: 1) Use the baseline (#1) to decide which tests run on the hosted runner; remove continue-on-error from the test step. 2) Run on pushes and pull requests to main and demo. 3) On a tag vYYYY.MM.PATCH build the release package (deploy/Build-Package.ps1 or a container image) and attach it to a GitHub release with commit and build number. 4) Document it in docs/deployment. | J8: Done when: a red test fails the workflow; a tag produces a release artifact with version, commit and build number; no secret is stored in the repository. | K8: PM 2026-10-18: basic CI first; no dependency on the workflow foundation. | L8: M0 | M8: M | N8: High | O8: #1 | P8: Titan #119 | R8: DevOps & release | S8: Yes | T8: Sprint 1 | U8: Member B
A9: 8 | B9: Claude | C9: Foundation, Architecture Decisions & Baseline | D9: Repository cleanup: stray folders and duplicate documents (.claude/Role vs .github/Role) | E9: Tech Debt | F9: Not Started | G9: P2 | H9: The root contains WebApplication1, 'New Text Document.txt' and two identical copies of the Role documents under .claude and .github. 2026-10-28 plan audit: dependency/milestone corrected (see docs/audits/2026-10-28-dynamic-restful-audit.md). | I9: Remove or archive anything unused and pick one official location for the Role documents. | J9: The repo builds without unused folders and the Role documents have one official home. | L9: M1 | M9: S | N9: Low | R9: Foundation & decisions | S9: No
A10: 9 | B10: Claude | C10: Foundation, Architecture Decisions & Baseline | D10: Audit the repository, history and container files for secrets and unsafe defaults, and fix what remains | E10: Bug Fix | F10: Not Started | G10: P0 | H10: Default connection strings or keys inside source are a sales blocker. appsettings.json/UAT/Development in PEMS.Web have not been reviewed. | I10: 1) Confirm HEAD has no secret (env files done in #315; check docker-compose.yml, Dockerfile, workflows, scripts). 2) Search the git history for secrets that were ever committed (for example the old default admin password and any connection strings) and list them. 3) For each finding record: fixed, needs rotation (give to #317), or accepted. Output: docs/audits/SECRETS_AUDIT_2026-10.md. | J10: Done when: the report exists; HEAD is clean; every historical finding has a decision and an owner. | K10: Merged 2026-10-26 (PR atapems-tech/PEMS#6, merge bc717dc): HEAD and full history (202 commits, all refs) scanned; no tokens, keys or real connection strings; five built-in passwords found and removed from HEAD (default administrator, employee-created users, compose SQL sa fallback, load-test accounts, weak example); rotation list and runbook handed to #317; held follow-ups #374 and #375; open items in docs/audits/SECRETS_AUDIT_2026-10.md. Tests NOT run (no .NET SDK): the row is Done only after the build and the new tests pass. | L10: M0 | M10: S | N10: Sales blocker | P10: Titan #137 | R10: Foundation & decisions | S10: No | T10: Sprint 1 | U10: Member B
A11: 10 | B11: Claude | C11: Metadata Core & Dynamic Platform | D11: Registry for apps/modules/entities/fields/relations with versioning | E11: Feature | F11: Not Started | G11: P0 | H11: PEMS has no general App/Entity/Field registry (audit E1/E2). The proven pattern is that everything is a database row, not code. 2026-10-28: design in docs/architecture/METADATA_REGISTRY_DESIGN.md (ADR-0010); payload and lifecycle follow the definition envelope. | I11: Design and build the metadata model (App, Module, Entity, Field, Relation, OptionSet, View, Form, Menu, StatusSet) with Draft/Published/Retired states. | J11: A sample entity is created, published and used for CRUD purely through metadata rows (no new C# code); metadata changes apply without build/redeploy. | L11: M1 | M11: XL | N11: Sales blocker | O11: #4 #3 | P11: Titan #61 | Q11: OLD-4 OLD-5 OLD-6 | R11: Dynamic data core | S11: No
A12: 11 | B12: Claude | C12: Metadata Core & Dynamic Platform | D12: Field type catalog: text, number, decimal, date (Jalali/Gregorian), boolean, single/multi select, lookup, user, file, rich text, computed, auto-number, JSON | E12: Feature | F12: Not Started | G12: P0 | H12: A single type definition from day one avoids the field-type vs column-type duplication seen in comparable platforms. 2026-10-28: design in docs/architecture/METADATA_REGISTRY_DESIGN.md (ADR-0010); payload and lifecycle follow the definition envelope. | I12: For every type define storage, validation, form/grid rendering, filtering, sorting, import/export and localization. | J12: A 'type x (storage/form/grid/filter/export)' matrix is complete and covered by automated tests. | L12: M1 | M12: L | N12: Sales blocker | O12: #10 | P12: Titan #19 | R12: Dynamic data core | S12: No
A13: 12 | B13: Claude | C13: Metadata Core & Dynamic Platform | D13: Generic dynamic CRUD/Query API with server-side paging, filter, sort and mandatory RLS | E13: Feature | F13: Not Started | G13: P0 | H13: Server-side paging above ~1,000 rows regressed twice on a comparable platform; one query contract from the start is required. 2026-10-28: REST inventory done, see docs/audits/REST_INVENTORY_2026-10-28.md and rest-inventory.csv (#432). | I13: Build one /api/d/{entity} endpoint with a single query contract (page/sort/filter/search/columns) used by every list and relation list. Route shape, paging style and error format come from the REST ADR (#431), not from this row; the first version must pass the API quality gates (#436). | J13: Test: 500k records, filter+sort under 500 ms; a record outside the user's access never appears in results or counts. The route and contract follow the REST API standard (#431): resource-oriented URLs instead of verbs, ETag/If-Match, RFC 9457 errors, OpenAPI. | L13: M1 | M13: XL | N13: Sales blocker | O13: #10 #11 #178 #431 #435 | P13: Titan #49 #136 | Q13: OLD-89 OLD-20 | R13: Dynamic data core | S13: No
A14: 13 | B14: Claude | C14: Metadata Core & Dynamic Platform | D14: Safe schema-change planner: add/delete/change field type with impact preview, approval and rollback | E14: Feature | F14: Not Started | G14: P0 | H14: Changing a field type on live data is the riskiest operation of any dynamic platform. 2026-10-28: design in docs/architecture/METADATA_REGISTRY_DESIGN.md (ADR-0010); payload and lifecycle follow the definition envelope. | I14: Generate a change plan: affected row count, data-loss risk, generated SQL, automatic backup and rollback path. | J14: Unsafe changes are blocked without two-step approval; rollback test on sample data succeeds. | L14: M1 | M14: XL | N14: Sales blocker | O14: #10 | P14: Titan #17 | Q14: OLD-88 | R14: Dynamic data core | S14: No
A15: 14 | B15: Claude | C15: Metadata Core & Dynamic Platform | D15: Physical storage generator (DDL) and JSON extension column for custom fields on static entities | E15: Feature | F15: Not Started | G15: P0 | H15: Customers must add a field to a static entity such as Equipment or WorkOrder without a code migration. | I15: Per the storage ADR: create/alter tables, indexes and foreign keys; store custom fields in a JSON column with computed indexes for filtering. | J15: A custom field added to Equipment in the UI, with no deploy, appears in list/form/export/search. | L15: M1 | M15: L | N15: Sales blocker | O15: #13 | R15: Dynamic data core | S15: No
A16: 15 | B16: Claude | C16: Metadata Core & Dynamic Platform | D16: Shared expression/formula engine for computed fields, validation and conditions | E16: Library Modernization | F16: Not Started | G16: P0 | H16: One formula engine should drive automatic values and validation; today each module has its own logic. | I16: Select an expression library (F_LIBS) and sandbox it: Jalali date functions, Persian text, relation lookups, time and memory limits. | J16: The same expression yields the same result on client, server and reports; a malicious expression (infinite loop) is stopped. | L16: M1 | M16: L | N16: High | O16: #6 | P16: Titan #12 | R16: Dynamic data core | S16: No
A17: 16 | B17: Claude | C17: Metadata Core & Dynamic Platform | D17: Configurable auto-numbering (pattern, Jalali/Gregorian year, periodic reset) with DB-enforced uniqueness | E17: Feature | F17: Partial | G17: P1 | H17: A serial that is sequential but not unique in the DB is a known defect pattern. Engineering documents and work orders need traceable numbers. | I17: Patterns such as WO-{YYYY}-{#####}; atomic allocation with DB locking and a unique index. | J17: A 50-parallel-request test yields no duplicate numbers; the pattern is editable and versioned. | K17: 2026-10-28 SCRUM-40: patterns per document type (NumberingSchemes, Admin > Numbering: tokens YYYY/YY Jalali or Gregorian, PROJECT, DISC, SEQ; yearly or no reset; manual entry flag; version + audit) applied to all procurement documents (MR, package, tender, bid, PO, contract); atomic counter per scope, existing numbers skipped, 50-parallel SQL test without duplicates. Other modules (work order, IRN, ...) still use the built-in formats. | L17: M4 | M17: M | N17: High | O17: #10 | P17: Titan #16 | R17: Dynamic data core | S17: No
A18: 17 | B18: Claude | C18: Metadata Core & Dynamic Platform | D18: Generic change audit (field-level history) for every dynamic entity | E18: Feature | F18: Not Started | G18: P0 | H18: Current audit covers access only (AuthorizationAuditLog). Selling to oil/petrochemical requires per-field change history. | I18: On every create/update/delete record who, when, before/after value and form/metadata version; show in a History tab. | J18: Each record's history is viewable, filterable and exportable and cannot be deleted manually. | L18: M1 | M18: L | N18: High | O18: #12 | Q18: OLD-58 | R18: Dynamic data core | S18: No
A19: 18 | B19: Claude | C19: Metadata Core & Dynamic Platform | D19: Concurrency control: optimistic rowversion plus live edit lock showing the lock holder | E19: Feature | F19: Not Started | G19: P1 | H19: PEMS has SignalR hubs but no generic record lock. Real-time and locking is a new subsystem, not an extension. 2026-10-28: follows the REST API standard ADR-0009 / guideline chapter 08 (#431). | I19: Locks with safe expiry, release on disconnect, auditable conflicts. | J19: Two users on one record: the second sees 'being edited by ...'; simultaneous saves never silently overwrite. | L19: M4 | M19: L | N19: Medium | O19: #12 | P19: Titan #104 | Q19: OLD-93 | R19: Dynamic data core | S19: No
A20: 19 | B20: Claude | C20: Metadata Core & Dynamic Platform | D20: Generic attachments, comments and activity (chatter) for any entity | E20: Feature | F20: Not Started | G20: P1 | H20: Each module has its own attachments/comments today; one shared component and model is needed. | I20: A polymorphic attachment/comment table whose RLS is inherited from the parent record, using the hardened upload path. | J20: One checkbox on an entity turns attachments/comments on. | L20: M4 | M20: M | N20: High | O20: #12 #183 | R20: Dynamic data core | S20: No
A21: 20 | B21: Claude | C21: Metadata Core & Dynamic Platform | D21: Menu generation from metadata with access filtering and orphan-controller test | E21: Feature | F21: Not Started | G21: P0 | H21: The current menu in _SidebarMenu.cshtml is static. 2026-10-28 audit: the designer saves through the definition store API (#434), not its own storage. 2026-10-28: the stored shape follows ADR-0011 (UI definition model). | I21: Tree menu from metadata (order, icon, grouping, license/access conditions); automated test for controllers with no menu entry. | J21: The menu updates with no code change when a module is added; items without permission are not shown. | K21: PM 2026-10-18: raised to P0/M2 (module wizard depends on it). | L21: M2 | M21: M | N21: High | O21: #10 #434 | Q21: OLD-7 | R21: Dynamic data core | S21: Yes
A22: 21 | B22: Claude | C22: Metadata Core & Dynamic Platform | D22: Managed Reference/OptionSet type: value lists with history and translation | E22: Feature | F22: Not Started | G22: P1 | H22: Selectable values must be translatable and carry history. | I22: OptionSet with value/label (Persian and English)/color/active flag and cascading dependencies (e.g. unit to equipment). | J22: Changing a value's label is correct on existing records and is audited. | L22: M4 | M22: M | N22: Medium | O22: #10 | P22: Titan #138 #230 | R22: Dynamic data core | S22: No
A23: 22 | B23: Claude | C23: Metadata Core & Dynamic Platform | D23: Relation registry and generalized Relationship Explorer with RLS on every node and edge | E23: Feature | F23: Not Started | G23: P1 | H23: PEMS already has a Relationship Explorer service (Done) but relations are hard-coded. | I23: Relations with cardinality, label, cascade, snapshot and permission; the relation graph is read from the registry. | J23: A relation added in the UI appears in the explorer and a forbidden node is never shown. | L23: M4 | M23: L | N23: High | O23: #10 | Q23: OLD-32 OLD-36 | R23: Dynamic data core | S23: No
A24: 23 | B24: Claude | C24: Metadata Core & Dynamic Platform | D24: Signed metadata package (export/import) and Dev-to-Test-to-Prod promotion | E24: Feature | F24: Not Started | G24: P0 | H24: Customers need to build modules/forms/workflows in test and promote them; without this dynamic behavior is unsafe in production. | I24: A JSON/zip package with dependencies, diff, approval, smoke test, release note and rollback. | J24: A module package installs on a second instance and runs untouched; an incompatible package is rejected. | K24: PM 2026-10-18: raised to P0/M2 (module versions depend on it). | L24: M2 | M24: L | N24: High | O24: #10 | P24: Titan #150 | Q24: OLD-75 | R24: Dynamic data core | S24: Yes
A25: 24 | B25: Claude | C25: Metadata Core & Dynamic Platform | D25: Multilingual labels and messages in metadata (translatable strings, Persian default + English) | E25: Feature | F25: Not Started | G25: P1 | H25: Language/direction should be configurable at system/app/model/field level. PEMS currently sets DefaultRequestCulture to en in Program.cs. | I25: All metadata labels as a language map with a defined fallback; Persian is the product default. | J25: Changing a user's language changes labels only, never data. | L25: M4 | M25: M | N25: High | O25: #10 #205 | P25: Titan #190 | R25: Dynamic data core | S25: No
A26: 25 | B26: Claude | C26: Metadata Core & Dynamic Platform | D26: Dynamic import designer (template, column mapping, staging, review, commit, rollback) on any entity | E26: Feature | F26: Not Started | G26: P1 | H26: PEMS has 11 fixed imports (Import Center). Customers must build imports for their own modules. A partial update must not fail on an intentionally blank field. | I26: Auto-generate an Excel template from metadata, error preview, asynchronous run and row-level error report. | J26: A 50k-row import with row-level errors and full rollback; import permission uses the same RLS. | L26: M4 | M26: L | N26: High | O26: #12 | P26: Titan #13 | Q26: OLD-56 OLD-57 | R26: Dynamic data core | S26: No
A27: 26 | B27: Claude | C27: Metadata Core & Dynamic Platform | D27: A field with a default value must never persist as NULL (including bulk paths) | E27: Tech Debt | F27: Not Started | G27: P2 | H27: Bulk and import paths bypass defaults on comparable platforms. | I27: Apply a DEFAULT constraint in the DB and enforce it in bulk/import paths. | J27: A bulk test shows no NULL for defaulted fields. | L27: M5 | M27: S | N27: Low | O27: #14 | P27: Titan #14 | R27: Dynamic data core | S27: No
A28: 27 | B28: Claude | C28: Metadata Core & Dynamic Platform | D28: Duplicate-record merge tool (pick the winning value per field, replace FKs, soft-delete the loser) | E28: Feature | F28: Not Started | G28: P3 | H28: Useful for cleaning migrated data. | I28: A merge wizard with preview and audit. | J28: Merging two duplicate equipment records moves every reference. | L28: M6 | M28: L | N28: Low | O28: #12 | P28: Titan #9 | R28: Dynamic data core | S28: No
A29: 28 | B29: Claude | C29: Metadata Core & Dynamic Platform | D29: Metadata cache with invalidation on write and ETag/gzip for static responses | E29: Tech Debt | F29: Not Started | G29: P0 | H29: A cached registry (TTL + write invalidation) with ETag/gzip cured slow database access on a comparable platform; a registry change must not need a rebuild. 2026-10-28: follows the REST API standard ADR-0009 / guideline chapter 08 (#431). 2026-10-28: design in docs/architecture/METADATA_REGISTRY_DESIGN.md (ADR-0010); payload and lifecycle follow the definition envelope. | I29: In-memory cache keyed by metadata version; coherent invalidation across instances. | J29: A metadata change takes effect on all instances in under 2 seconds; database load for reading metadata is near zero. | L29: M1 | M29: M | N29: High | O29: #10 | P29: Titan #50 #61 | R29: Dynamic data core | S29: No
A30: 29 | B30: Claude | C30: Component Library & Design System | D30: Finish the UI pattern audit: review the 30 heaviest pages by hand and compute the convertible percentage per migration wave | E30: Research | F30: Partial | G30: P0 | H30: Views are page-specific, with separate CSS/JS (pems-data-grid, pems-vdr, pems-global-search). No pattern inventory exists. 2026-10-23 static audit run (tools/UiAudit/pattern-audit.py): 339 views = 303 pages + 36 partials; list 141, form 61 (+20 small), dashboard 26, table-only 32, detail 10, other 13; 2,587 hand-written inputs vs 202 asp-for; 342 tables, 108 modals, 846 badges; 632 inline styles in 197 views, 89 inline scripts; only 33/303 pages use the page header, 8 an empty state, 3 a loading state. Per-view table 'view -> pattern -> target component -> wave' is docs/design/ui-pattern-audit.csv; summary docs/design/UI_PATTERN_AUDIT.md. | I30: 1) Open docs/design/UI_PATTERN_AUDIT.md and extend its heaviest-pages list to 30. 2) For each page decide A (convertible with the planned components as is), B (needs a new component) or C (stays custom); record the new components B needs. 3) Add the percentages per wave to the audit document. 4) Re-run python tools/UiAudit/pattern-audit.py --md and commit the refreshed files. | J30: Done when: the audit document lists A/B/C for 30 pages and the percentage per wave W1-W5; the list of missing components feeds rows #322-#325. | K30: Static inventory done; the 'convertible percentage' and manual review of the heaviest pages remain (rerun the script per wave). | L30: M0 | M30: M | N30: Sales blocker | Q30: OLD-96 | R30: UI component library | S30: No | T30: Sprint 1 | U30: Member B
A31: 30 | B31: Claude | C31: Component Library & Design System | D31: Consolidate the design tokens into one file and remove hard-coded colours from the shared CSS | E31: Feature | F31: Not Started | G31: P0 | H31: Foundation for white-labeling (BRD) and UI consistency; content density should be configurable. 2026-10-23 audit: 21 CSS files / 4,554 lines, 642 hard-coded hex colours vs 753 var(--pems-*) uses, 65 physical left/right rules (RTL); .vs-* workspace system and --pems tokens already exist and are the starting point. | I31: 1) Create PEMS.Web/wwwroot/css/tokens.css (moves into PEMS.UI later, #320) with colour, typography (Persian and English), spacing, radius, elevation, density, status and chart palette, for the Light, Dark and Turquoise themes. 2) Replace the 642 hex colours in the shared CSS (pems-workspace.css, pems-themes.css, site.css, administration-design-system.css) with tokens. 3) Replace physical left/right rules (65 in the audit) with logical properties. 4) Compare screenshots before and after in LTR and RTL. | J31: Done when: the four listed CSS files contain no hex colours and no physical left/right rules; screenshots show no visible change; the token file is documented in docs/design/WORKSPACE_DESIGN_SYSTEM.md. | L31: M1 | M31: M | N31: High | O31: #5 | P31: Titan #192 #128 | Q31: OLD-95 | R31: UI component library | S31: No | T31: Sprint 1 | U31: Member B
A32: 31 | B32: Claude | C32: Component Library & Design System | D32: Core component library: button, inputs, select/lookup, date/time, upload, modal, drawer, tabs, badge, tooltip, empty/error/loading states | E32: Feature | F32: Not Started | G32: P0 | H32: Buttons, chips and loading states must be unified under one API. 2026-10-23: decomposed into #322 fields/form shell, #323 data display and skeletons, #324 overlays/navigation, #325 page templates; project, contract and gates in #320, #321, #326, #327. | I32: Components with a consistent API, documented, with no inline styles. | J32: 100% of components in the form/grid vertical slice use only the library. | L32: M1 | M32: XL | N32: Sales blocker | O32: #30 #5 #320 #321 | P32: Titan #41 #121 #122 #244 | Q32: OLD-96 | R32: UI component library | S32: No
A33: 32 | B33: Claude | C33: Component Library & Design System | D33: Enterprise data grid: server-side paging, filter, saved views, column picker, pinning, bulk actions, export, density, virtualization | E33: Feature | F33: Not Started | G33: P0 | H33: The current grid (pems-data-grid.js) is page-specific. This is the most visible component in a sales demo. | I33: Build the grid on the D_API contract; RTL, 100k-row speed, per-user/role saved views. | J33: Every list in the vertical slice uses this grid and becomes interactive within 5 seconds. | L33: M1 | M33: XL | N33: Sales blocker | O33: #12 #31 | P33: Titan #53 #139 | Q33: OLD-97 OLD-90 | R33: UI component library | S33: No
A34: 33 | B34: Claude | C34: Component Library & Design System | D34: View types: list, tree, cards/gallery, Kanban/status board, calendar (Jalali+Gregorian), timeline/Gantt | E34: Feature | F34: Not Started | G34: P1 | H34: A calendar view available by default on every model is a proven need; CMMS scheduling depends on it. | I34: Each view is configured from entity metadata (date field, grouping). | J34: A dynamic entity gets a calendar/kanban view by toggling it, with no code. | L34: M4 | M34: L | N34: High | O34: #32 | P34: Titan #179 #36 | Q34: OLD-66 | R34: UI component library | S34: No
A35: 34 | B35: Claude | C35: Component Library & Design System | D35: Dynamic form component standards (sections, tabs, help text, conditional, attachments, drafts, dirty-state prompt, responsiveness) | E35: Feature | F35: Not Started | G35: P0 | H35: Foundation of FRM_RUN. | I35: Specify and build each form component with error, read-only and loading states. | J35: All states are visible and tested in the component gallery. | L35: M1 | M35: L | N35: High | O35: #31 | Q35: OLD-98 | R35: UI component library | S35: No
A36: 35 | B36: Claude | C36: Component Library & Design System | D36: Lookup/Relation picker and TreeSelect (unit, PBS, equipment) with server-side search | E36: Feature | F36: Partial | G36: P1 | H36: Parent selectors and tree selects must be library-based and optimized. | I36: Debounced search, paging, RLS, multi-select. | J36: Selecting from 200k equipment records is smooth. | K36: 2026-10-28 SCRUM-57: searchable select on every form (PEMS.UI pems-select.js on vendored Tom Select, loaded by the layout; >=8 options automatic, data-pems-select-source for permission-aware server search via /SearchApi, opt-out, inline in modals/dropdowns, cascading refresh, RTL/dark, fa/en). TreeSelect (unit/PBS) and paging beyond the first 20 server results are still open. | L36: M4 | M36: M | N36: High | O36: #12 #31 | P36: Titan #33 #47 | R36: UI component library | S36: No
A37: 36 | B37: Claude | C37: Component Library & Design System | D37: Workflow/status components: timeline, badge, action bar, delegation, escalation, comments, audit trail | E37: Feature | F37: Not Started | G37: P1 | H37: PEMS has static _PemsStageDiagram and _WorkOrderStagesDiagram. 2026-10-28 plan audit: dependency/milestone corrected (see docs/audits/2026-10-28-dynamic-restful-audit.md). | I37: Convert them to data-driven components fed by the workflow runtime. | J37: Every dynamic process gets these components without code. | L37: M4 | M37: M | N37: High | O37: #31 | Q37: OLD-99 | R37: UI component library | S37: No
A38: 37 | B38: Claude | C38: Component Library & Design System | D38: Safe rich-text editor (RTL/LTR) with HTML sanitization | E38: Feature | F38: Partial | G38: P2 | H38: A partial _RichTextEditorScripts.cshtml and HtmlSanitizer exist; they need standardizing and integration with the form builder. | I38: Turn it into a standard field type. | J38: A rich-text field in the form builder is sanitized on the server. | L38: M5 | M38: S | N38: Low | O38: #11 | P38: Titan #231 | R38: UI component library | S38: No
A39: 38 | B39: Claude | C39: Component Library & Design System | D39: Accessibility standard (contrast, focus, keyboard, labels, errors) | E39: Feature | F39: Not Started | G39: P1 | H39: Often required in enterprise and government contracts. 2026-10-28 plan audit: dependency/milestone corrected (see docs/audits/2026-10-28-dynamic-restful-audit.md). | I39: A checklist and automated axe tests in CI. | J39: Core components have no serious axe violations. | L39: M1 | M39: M | N39: Medium | O39: #31 | Q39: OLD-100 | R39: UI component library | S39: No
A40: 39 | B40: Claude | C40: Component Library & Design System | D40: Responsive QA matrix (desktop/tablet/mobile) for list, form, detail, dashboard, kanban | E40: Feature | F40: Not Started | G40: P1 | H40: A working mobile view for every screen type must be verified, not assumed. PEMS has manifest.json and service-worker.js. | I40: Matrix plus browser tests. | J40: No main page is broken at 375px. | L40: M4 | M40: M | N40: High | O40: #32 | P40: Titan #177 | Q40: OLD-102 | R40: UI component library | S40: No
A41: 40 | B41: Claude | C41: Component Library & Design System | D41: Component gallery (Storybook-style) with RTL examples and usage guidance | E41: Docs | F41: Not Started | G41: P1 | H41: Needed by partner/customer developers and for technical sales. 2026-10-23: implemented as the catalog host in PEMS.UI by #326. | I41: An internal site showing states and sample code. | J41: Each component has a page. | K41: PM 2026-10-18: raised to P1 (visual regression depends on it). | L41: M4 | M41: M | N41: Medium | O41: #31 | Q41: OLD-103 | R41: UI component library | S41: Yes
A42: 41 | B42: Claude | C42: Component Library & Design System | D42: Visual regression tests (Playwright) in RTL/LTR and multiple sizes | E42: Tech Debt | F42: Not Started | G42: P1 | H42: Prevents accidental UI breakage when tokens or libraries change. | I42: Snapshots of critical pages in CI. | J42: An unintended visual change turns the PR red. | L42: M4 | M42: M | N42: Medium | O42: #40 | P42: Titan #117 | Q42: OLD-104 | R42: UI component library | S42: No
A43: 42 | B43: Claude | C43: Component Library & Design System | D43: Make the UI fully offline: replace the cdnjs pdf.js references with a local copy and add a check that fails on external URLs in views | E43: Tech Debt | F43: Not Started | G43: P0 | H43: Production has no internet. wwwroot/lib is local but scripts and fonts have not been checked. 2026-10-23 found 4 references to cdnjs.cloudflare.com (pdf.js script and worker) in Views/EngineeringDocuments/Details.cshtml and Views/VDR/Details.cshtml - violates Instructions rule 1; vendor pdf.js locally (no CDN) as part of #333. | I43: 1) Add pdf.js 4.0.379 under PEMS.Web/wwwroot/lib/pdfjs (record its licence in row #121). 2) Replace the script and worker URLs in Views/EngineeringDocuments/Details.cshtml (about line 1192) and Views/VDR/Details.cshtml (about line 324). 3) Make tools/UiAudit/pattern-audit.py exit with an error when a view references http(s) CDN hosts. 4) Test the PDF preview with the network disabled. | J43: Done when: no .cshtml references an external host; the PDF preview works offline in both viewers; the audit check runs in CI (#327 will reuse it). | K43: 2026-10-27 (SCRUM-20, Claude for Hamid): pdf.js 4.0.379 vendored under PEMS.Web/wwwroot/lib/pdfjs (npm pdfjs-dist, Apache-2.0, hashes in README-PEMS.txt); 4.x is ES-module only, so both viewers load it through wwwroot/js/pdfjs-loader.js. cdnjs references removed from Engineering Documents and VDR Details. OfflineAssetsTests (4) scan views, areas, PEMS.UI, wwwroot js/css for external hosts (allow-list: www.w3.org, learn.microsoft.com, www.iso.org placeholder); tools/UiAudit/pattern-audit.py exits 1 on a CDN reference. Tests: OfflineAssetsTests 4/4 and mutation (a cdnjs reference in a view fails it); audit script exit 1/0; Chromium with all external requests blocked rendered a PDF through the loader (0 external requests, 0 page errors); inline scripts parse as strict-mode modules. Not run: the two real pages in the running app (needs SQL Server and a login) - README M-17. | L43: M0 | M43: S | N43: High | P43: Titan rule 1 | R43: UI component library | S43: No | T43: Sprint 1 | U43: Member B
A44: 43 | B44: Claude | C44: Component Library & Design System | D44: Global search and Command Palette (menus, records, actions) with RLS | E44: Feature | F44: Partial | G44: P2 | H44: GlobalSearch and pems-global-search.js exist; menu/action coverage and the security contract of providers are incomplete. | I44: Upgrade to a palette (Ctrl+K) and a security contract for every ISearchableEntityProvider. | J44: Search results never show a record the user cannot access. | L44: M5 | M44: M | N44: Medium | O44: #178 | P44: Titan #199 | Q44: OLD-22 | R44: UI component library | S44: No
A45: 44 | B45: Claude | C45: Dynamic Form Builder | D45: Visual form designer (sections, tabs, columns, child tables, attachments, live preview, translation) | E45: Feature | F45: Not Started | G45: P0 | H45: PEMS forms are fixed Razor; the audit found no general form builder. This is the line between software and a platform. 2026-10-28 audit: the designer saves through the definition store API (#434), not its own storage. 2026-10-28: the stored shape follows ADR-0011 (UI definition model). | I45: Drag fields from the catalog, set fractional widths, preview with sample data and different roles. | J45: An authorized user builds a 20-field 'safety inspection' form with 2 tabs and a child table in 10 minutes or less and publishes it. | L45: M2 | M45: XL | N45: Sales blocker | O45: #10 #34 #434 | P45: Titan #43 | Q45: OLD-8 | R45: Form builder | S45: No
A46: 45 | B46: Claude | C46: Dynamic Form Builder | D46: Form runtime from metadata with save, audit and form version | E46: Feature | F46: Not Started | G46: P0 | H46: The heart of dynamism; one set of components for create/edit/view/print. | I46: Render from form JSON, validate on client and server, store the form version on the record. | J46: Changing a published form does not corrupt older records (versioned). | L46: M2 | M46: XL | N46: Sales blocker | O46: #44 #12 | Q46: OLD-9 | R46: Form builder | S46: No
A47: 46 | B47: Claude | C47: Dynamic Form Builder | D47: Validation rule builder (required, regex, range, uniqueness, lookup existence, cross-field, server-only) | E47: Feature | F47: Not Started | G47: P0 | H47: All rules should live in one validation object with one interpreter. 2026-10-28 plan audit: dependency/milestone corrected (see docs/audits/2026-10-28-dynamic-restful-audit.md). | I47: A rule UI with identical server/client execution and translatable messages. | J47: Every rule has a unit test; import and API honor the same rules. | L47: M2 | M47: L | N47: High | O47: #15 #45 #355 | P47: Titan #10 #11 #12 | Q47: OLD-10 | R47: Form builder | S47: No
A48: 47 | B48: Claude | C48: Dynamic Form Builder | D48: Conditional visibility/editability/required by role, unit, project, confidentiality, workflow status and field value | E48: Feature | F48: Not Started | G48: P0 | H48: Core need of permit-to-work, MOC and NCR forms. | I48: A visual condition editor with server-side evaluation (UI is only a hint). | J48: A hidden field is not returned by the API either. | L48: M2 | M48: L | N48: High | O48: #45 #181 | P48: Titan #83 | Q48: OLD-11 | R48: Form builder | S48: No
A49: 48 | B49: Claude | C49: Dynamic Form Builder | D49: Child table (line items) inside a form with computed totals | E49: Feature | F49: Not Started | G49: P0 | H49: Purchase requests, work orders and parts lists need it; modeling resources as a child model is a proven approach. | I49: Child rows with validation, ordering and sum/average. | J49: Entering 200 child rows is not slow. | L49: M2 | M49: L | N49: High | O49: #45 | P49: Titan #85 | R49: Form builder | S49: No
A50: 49 | B50: Claude | C50: Dynamic Form Builder | D50: Form versioning and field-migration assistant (map old field to new) | E50: Feature | F50: Not Started | G50: P1 | H50: Records must stay viewable under the old form version. | I50: Version diff, mapping, batch execution. | J50: Upgrading a form with 10k records loses no data. | L50: M4 | M50: L | N50: High | O50: #45 #13 | Q50: OLD-13 | R50: Form builder | S50: No
A51: 50 | B51: Claude | C51: Dynamic Form Builder | D51: Field-level security: hide, mask, read-only, require step-up before reveal | E51: Feature | F51: Not Started | G51: P1 | H51: WebAuthn/FIDO2 already exists and can serve as step-up. | I51: Field policy in metadata, enforced on the server. | J51: A sensitive field is not visible in API/export without step-up. | L51: M4 | M51: M | N51: High | O51: #181 | Q51: OLD-12 | R51: Form builder | S51: No
A52: 51 | B52: Claude | C52: Dynamic Form Builder | D52: Cascading lookups (dependent filters between fields) and data sources from relations/OptionSets | E52: Feature | F52: Not Started | G52: P1 | H52: Example: unit to system to equipment. | I52: Dependent filter configuration in the designer. | J52: Choosing the parent restricts the child's options. | L52: M4 | M52: M | N52: Medium | O52: #21 #35 | R52: Form builder | S52: No
A53: 52 | B53: Claude | C53: Dynamic Form Builder | D53: Ready form template library (permit to work, MOC, NCR, inspection, minutes, work request) | E53: Feature | F53: Not Started | G53: P1 | H53: Templates are both teaching samples and sellable value (template packs). | I53: Each template ships with form + workflow + report + sample data. | J53: Installing a template takes one click on a clean instance. | L53: M4 | M53: L | N53: Sales blocker | O53: #45 #67 | Q53: OLD-86 OLD-110 | R53: Form builder | S53: No
A54: 53 | B54: Claude | C54: Dynamic Form Builder | D54: Electronic/image signature field and templated printable forms (PDF) | E54: Feature | F54: Not Started | G54: P2 | H54: PEMS already has QuestPDF. E-signature for contract/work-order/document sign-off is a recognized need. | I54: A signature field type and a designable print template. | J54: Output PDF carries the signature and a tracking number. | L54: M5 | M54: M | N54: Medium | O54: #45 | P54: Titan #197 | R54: Form builder | S54: No
A55: 54 | B55: Claude | C55: Dynamic Form Builder | D55: Multi-step wizard forms with draft and autosave | E55: Feature | F55: Not Started | G55: P2 | H55: Closing step 2 must not close step 1, and open-form state should live in the URL. | I55: A form state machine plus URL state. | J55: Back/refresh does not lose data. | L55: M5 | M55: M | N55: Low | O55: #45 | P55: Titan #37 #40 | R55: Form builder | S55: No
A56: 55 | B56: Claude | C56: Dynamic Form Builder | D56: Public form via token link for contractors/vendors without an account | E56: Feature | F56: Not Started | G56: P3 | H56: Useful for VDR/TQ with external parties. | I56: One-time link, rate limit, captcha. | J56: A contractor with no account fills the form and attaches files. | L56: M6 | M56: M | N56: Medium | O56: #45 #183 | P56: Titan #178 | R56: Form builder | S56: No
A57: 56 | B57: Claude | C57: Dynamic Module Builder | D57: Module creation wizard: app + module + entities + menu + base permissions | E57: Feature | F57: Not Started | G57: P0 | H57: Without a guided scaffold the 'module builder' is only a table builder. 2026-10-28 audit: the designer saves through the definition store API (#434), not its own storage. | I57: A five-step wizard with starter templates and preview. | J57: An authorized user builds a 'Lab Asset Management' module with no developer. | L57: M2 | M57: L | N57: Sales blocker | O57: #10 #44 #20 #434 | P57: Titan #30 | R57: Module builder | S57: No
A58: 57 | B58: Claude | C58: Dynamic Module Builder | D58: View designer (columns, saved filters, grouping, conditional coloring, column sizes) | E58: Feature | F58: Not Started | G58: P0 | H58: List sizes must be structured metadata, not ad-hoc. 2026-10-28 audit: the designer saves through the definition store API (#434), not its own storage. 2026-10-28: the stored shape follows ADR-0011 (UI definition model). | I58: A view designer with sharing across roles. | J58: A view is saved and published to roles. | L58: M2 | M58: L | N58: High | O58: #32 #434 | P58: Titan #32 #52 | R58: Module builder | S58: No
A59: 58 | B59: Claude | C59: Dynamic Module Builder | D59: Per-module dashboard designer (KPI, chart, list, reference date, cross-filter) | E59: Feature | F59: Not Started | G59: P1 | H59: PEMS has a fixed engineering dashboard and DashboardSettings. Cross-filter dashboards driven by a formula engine are proven; a drag-drop editor is the gap. | I59: Widgets driven by saved queries with RLS. | J59: A dashboard built with no code, with cross-filtering and PDF. | L59: M4 | M59: XL | N59: High | O59: #12 #31 | P59: Titan #101 #102 #103 | R59: Module builder | S59: No
A60: 59 | B60: Claude | C60: Dynamic Module Builder | D60: Report designer (fields, filters, grouping, charts, scheduled delivery, Excel/PDF export) with RLS | E60: Feature | F60: Not Started | G60: P1 | H60: Current outputs are fixed QuestPDF reports. | I60: A designer plus asynchronous execution plus print template. | J60: A weekly scheduled report emails only the data the recipient may see. | L60: M4 | M60: XL | N60: High | O60: #12 #210 | Q60: OLD-59 | R60: Module builder | S60: No
A61: 60 | B61: Claude | C61: Dynamic Module Builder | D61: Module access designer: roles, RLS, rules and an editable permission matrix | E61: Feature | F61: Not Started | G61: P0 | H61: An editable authority matrix on unit/user forms is a proven pattern. | I61: A permission matrix UI on the existing RoleAssignment/Permission model. | J61: A new module is closed by default and only designated roles can access it. | L61: M2 | M61: L | N61: High | O61: #10 #178 | P61: Titan #1 #3 | R61: Module builder | S61: No
A62: 61 | B62: Claude | C62: Dynamic Module Builder | D62: Notification designer (template, event, audience, email/in-app/SMS) | E62: Feature | F62: Not Started | G62: P1 | H62: PEMS has a Notification folder. | I62: Templates with variables, scheduling, user preferences. | J62: A workflow event sends a notification in the user's language. | L62: M4 | M62: M | N62: High | O62: #10 #67 | P62: Titan #105 | R62: Module builder | S62: No
A63: 62 | B63: Claude | C63: Dynamic Module Builder | D63: Module package: install/uninstall, dependency graph and blocking unsafe disablement | E63: Feature | F63: Not Started | G63: P1 | H63: Audit E6: a module dependency graph is needed. | I63: Required/optional/historical dependencies; removal with impact preview. | J63: Removing a dependent module is blocked or leaves read-only historical links. | L63: M4 | M63: L | N63: High | O63: #23 | Q63: OLD-34 OLD-35 | R63: Module builder | S63: No
A64: 63 | B64: Claude | C64: Dynamic Module Builder | D64: Per-module settings page and product configuration center | E64: Feature | F64: Not Started | G64: P2 | H64: Settings should be grouped, validated, audited and exportable. | I64: A categorized settings UI with export/import. | J64: A setting change is audited. | L64: M5 | M64: M | N64: Medium | O64: #10 | P64: Titan #34 #114 | Q64: OLD-105 | R64: Module builder | S64: No
A65: 64 | B65: Claude | C65: Dynamic Module Builder | D65: Draft/test mode: try a module with sample data before publishing | E65: Feature | F65: Not Started | G65: P1 | H65: Without it customers test in production. | I65: A test area inside the same instance with separate data. | J65: A Draft module is visible only to its creator/testers. | L65: M4 | M65: M | N65: High | O65: #10 | R65: Module builder | S65: No
A66: 65 | B66: Claude | C66: Dynamic Module Builder | D66: Self-service kanban/task boards (Trello-style) without admin setup | E66: Feature | F66: Not Started | G66: P3 | H66: Personal/team boards. | I66: Board creation by ordinary users. | J66: A regular user creates a board. | L66: M6 | M66: M | N66: Low | O66: #33 | P66: Titan #200 | R66: Module builder | S66: No
A67: 66 | B67: Claude | C67: Dynamic Module Builder | D67: Builder limits (custom modules, forms, workflows) are taken from the Supportability Matrix, not from the edition | E67: Feature | F67: Not Started | G67: P1 | H67: Owner decision 2026-10-18: limits follow the supportability matrix. The matrix is created now and is updated in every finished task. | I67: Enforce on the server, at publish time, the limits recorded in the Supportability Matrix (custom modules, forms per module, fields per entity, workflows). | J67: Exceeding a supported limit warns or blocks per the matrix, and the matrix value and the enforced value are the same number. | K67: Redefined 2026-10-18: limits come from the Supportability Matrix. | L67: M4 | M67: S | N67: Sales blocker | O67: #281 #56 | R67: Module builder | S67: No
A68: 67 | B68: Claude | C68: Workflow Studio & BPMS | D68: Visual workflow studio (stages, transitions, roles/users, actions, terminal states, versions) | E68: Feature | F68: Not Started | G68: P0 | H68: PEMS has WorkflowDefinition/Version/Stage/Transition and one runtime (Done) but no designer UI. An editable status-flow chart with drag and colors is a proven pattern. | I68: A canvas designer on an evaluated library (watch for display-license/watermark terms) with design-time validation. | J68: An authorized user builds a 5-stage parallel/sequential 'engineering document approval' flow and it runs on the existing runtime. | L68: M2 | M68: XL | N68: Sales blocker | O68: #6 | P68: Titan #28 #36 #227 | Q68: OLD-14 | R68: Workflow studio & BPMS | S68: No
A69: 68 | B69: Claude | C69: Workflow Studio & BPMS | D69: Activate SLA, timers, escalation, delegation and notifications in the runtime | E69: Feature | F69: Not Started | G69: P0 | H69: TimeoutHours and escalation fields exist in the schema but nothing executes them (audit E3). | I69: A scheduler (Hangfire or dedicated service) for deadlines; working calendar with Friday and Iranian public holidays. | J69: A stage past its deadline is automatically escalated or delegated and recorded. | L69: M2 | M69: L | N69: High | O69: #67 #206 | Q69: OLD-15 | R69: Workflow studio & BPMS | S69: No
A70: 69 | B70: Claude | C70: Workflow Studio & BPMS | D70: Version governance: published versions immutable; migrate or continue in-flight instances | E70: Feature | F70: Not Started | G70: P0 | H70: Main BPMS risk: changing a process must not break active instances. | I70: Draft -> Review -> Publish -> Retire; policy 'continue on old version' or 'migrate'. | J70: Publishing a new version does not break active instances and is reversible. | L70: M2 | M70: L | N70: High | O70: #67 | Q70: OLD-16 OLD-6 | R70: Workflow studio & BPMS | S70: No
A71: 70 | B71: Claude | C71: Workflow Studio & BPMS | D71: Decision tables and rule designer (versioned, testable, callable from workflow/forms/import/API) | E71: Feature | F71: Not Started | G71: P0 | H71: Needed for conditional routing (amount > X goes to the finance manager). | I71: A decision-table UI with an input/output tester. | J71: A decision table is called from a workflow and audited. | L71: M2 | M71: L | N71: High | O71: #15 | Q71: OLD-74 | R71: Workflow studio & BPMS | S71: No
A72: 71 | B72: Claude | C72: Workflow Studio & BPMS | D72: Unified 'My Work' inbox across all processes with deadline and priority | E72: Feature | F72: Not Started | G72: P0 | H72: A cross-model universal inbox and automatic ball-in-court derivation are proven needs. | I72: List the user's/role's/group's tasks from every dynamic and static module. | J72: A user sees and opens all overdue work on one page. | L72: M2 | M72: M | N72: Sales blocker | O72: #67 | P72: Titan #15 #170 #169 | R72: Workflow studio & BPMS | S72: No
A73: 72 | B73: Claude | C73: Workflow Studio & BPMS | D73: Bind a form to a stage: field permissions, form and actions per stage | E73: Feature | F73: Not Started | G73: P0 | H73: The form of each stage may differ (requester vs approver). | I73: Map stage to form and field policy. | J73: At the approval stage only the permitted fields are editable. | L73: M2 | M73: M | N73: High | O73: #67 #47 | R73: Workflow studio & BPMS | S73: No
A74: 73 | B74: Claude | C74: Workflow Studio & BPMS | D74: Parallel/join, sub-process, loop and conditional routing | E74: Feature | F74: Not Started | G74: P1 | H74: The runtime supports parallel stages; UI and tests for sub-process/loop are needed. | I74: Core BPMN patterns. | J74: A 3-way parallel instance with an any/all/quorum join works. | L74: M4 | M74: L | N74: High | O74: #67 | R74: Workflow studio & BPMS | S74: No
A75: 74 | B75: Claude | C75: Workflow Studio & BPMS | D75: Service tasks: call API/webhook, email, create/update record, run rule | E75: Feature | F75: Not Started | G75: P1 | H75: Without them it is only an approval flow, not a full BPMS. | I75: An action library with permissions and timeouts. | J75: A process calls an external webhook and retries on failure. | L75: M4 | M75: L | N75: High | O75: #67 #195 | R75: Workflow studio & BPMS | S75: No
A76: 75 | B76: Claude | C76: Workflow Studio & BPMS | D76: Triggers: record created/changed, schedule, inbound webhook | E76: Feature | F76: Not Started | G76: P1 | H76: Allows processes to start automatically. | I76: Register triggers in metadata. | J76: Creating a purchase request starts the approval process automatically. | L76: M4 | M76: M | N76: High | O76: #67 #194 | R76: Workflow studio & BPMS | S76: No
A77: 76 | B77: Claude | C77: Workflow Studio & BPMS | D77: Segregation of duties and workflow guards through AccessControlService with evidence | E77: Feature | F77: Not Started | G77: P1 | H77: PEMS has SoDPolicy (Done) but no general workflow guard. | I77: Configurable guard on a transition. | J77: An approver equal to the requester is blocked and logged. | L77: M4 | M77: M | N77: High | O77: #67 | Q77: OLD-17 | R77: Workflow studio & BPMS | S77: No
A78: 77 | B78: Claude | C78: Workflow Studio & BPMS | D78: Simulator: detect dead ends, roles with no members, unreachable stages and SoD conflicts | E78: Feature | F78: Not Started | G78: P1 | H78: Raises process design quality. | I78: A dry run with sample data. | J78: A faulty process cannot be published. | L78: M4 | M78: M | N78: Medium | O78: #67 #76 | Q78: OLD-18 | R78: Workflow studio & BPMS | S78: No
A79: 78 | B79: Claude | C79: Workflow Studio & BPMS | D79: Process analytics: cycle time, bottlenecks, SLA breaches, overdue leaderboard | E79: Feature | F79: Not Started | G79: P2 | H79: Funnel, per-step cycle time and overdue-by-assignee tiles are a known need. | I79: Ready dashboards from instance history. | J79: A bottleneck chart exists for every process. | L79: M5 | M79: L | N79: Medium | O79: #67 #58 | P79: Titan #171 | R79: Workflow studio & BPMS | S79: No
A80: 79 | B80: Claude | C80: Workflow Studio & BPMS | D80: Case management model: intake, triage, assignment, SLA, closure and reopen | E80: Feature | F80: Not Started | G80: P2 | H80: Needed for support requests and TQ. | I80: A case is an entity plus a flexible workflow. | J80: A case with no fixed path can be managed. | L80: M5 | M80: L | N80: Medium | O80: #67 | Q80: OLD-73 | R80: Workflow studio & BPMS | S80: No
A81: 80 | B81: Claude | C81: Workflow Studio & BPMS | D81: Runtime UI (history, delegation, escalation, comments, evidence) on the existing runtime | E81: Feature | F81: Not Started | G81: P1 | H81: PEMS has the runtime but no unified user experience. | I81: One status view for all processes. | J81: All processes share one status page. | L81: M4 | M81: M | N81: High | O81: #36 | R81: Workflow studio & BPMS | S81: No
A82: 81 | B82: Claude | C82: Workflow Studio & BPMS | D82: Evidence package: record state, history, comments, attachments, hashes and audit trail | E82: Feature | F82: Not Started | G82: P1 | H82: Value for audits and certification. | I82: A signed export. | J82: The package can be verified independently. | L82: M4 | M82: M | N82: High | O82: #17 #67 | Q82: OLD-58 | R82: Workflow studio & BPMS | S82: No
A83: 82 | B83: Claude | C83: Workflow Studio & BPMS | D83: Ready process templates (document approval, MOC, permit, work order) and conversion of today's fixed flows | E83: Feature | F83: Not Started | G83: P1 | H83: Fixed flows are hard-coded in DocumentWorkflow, Permit and MOC services. | I83: Convert each fixed flow into a versioned Definition. | J83: Behavior matches the old flow under acceptance tests. | K83: 2026-10-27 SCRUM-103: the flows were already definitions on the single engine; 10 of 13 were view-only (whitelist, no binding, module code reading stage names/actions). Added module contracts (PemsWorkflowContracts, validator CONTRACT_* errors), a pinned binding backfill (same version as the legacy path) and removed the whitelist: all 13 editable, edits that would break a module are refused, running instances keep their version. Acceptance: PemsWorkflowContractTests (35). Follow-ups: SCRUM-90 instance migration, BusinessStatus for document/MOC/TQ status. SM-43. | L83: M4 | M83: L | N83: Sales blocker | O83: #67 | Q83: OLD-110 | R83: Workflow studio & BPMS | S83: No
A84: 83 | B84: Claude | C84: Workflow Studio & BPMS | D84: Environment promotion of process definitions and smoke test | E84: Feature | F84: Not Started | G84: P1 | H84: Aligned with D_PKG. | I84: Sign and transfer the process package like a metadata package; diff, approval and smoke test before activation. | J84: A process moves from Test to Prod with a diff and approval. | L84: M4 | M84: M | N84: Medium | O84: #23 #67 | Q84: OLD-75 | R84: Workflow studio & BPMS | S84: No
A85: 84 | B85: Claude | C85: Workflow Studio & BPMS | D85: BPMN 2.0 import/export (optional) | E85: Feature | F85: Not Started | G85: P3 | H85: Competitive with modeling tools. | I85: Import/export simple definitions (task, gateway, event) mapped to the internal model; report unsupported elements explicitly. | J85: A simple sample round-trips. | L85: M6 | M85: M | N85: Low | O85: #67 | R85: Workflow studio & BPMS | S85: No
A86: 85 | B86: Claude | C86: Static-to-Dynamic Module Migration | D86: Classify every static module: fully convertible / hybrid / permanently static | E86: Research | F86: Not Started | G86: P0 | H86: 98 controllers and 91 view folders (Asset, Contract, Crew, Permit, WorkOrder, DocumentRegister, VDR, ...). 2026-10-28: REST inventory done, see docs/audits/REST_INVENTORY_2026-10-28.md and rest-inventory.csv (#432). | I86: A module table with risk, data volume, dependencies and migration wave. Also classify the ~303 pages and the 147 controllers: definable from a Page definition (#438), convertible form/list/detail, or code-only; reuse the REST inventory (#432). | J86: Every module has exactly one wave and one owner. | L86: M0 | M86: M | N86: Sales blocker | O86: #29 #432 | R86: Static-to-dynamic migration | S86: No
A87: 86 | B87: Claude | C87: Static-to-Dynamic Module Migration | D87: Strangler pattern and parity gate before removing a static version | E87: Docs | F87: Not Started | G87: P0 | H87: Without it migration is a production risk. | I87: Automated acceptance tests proving old/new behavior parity; redirect old URLs. | J87: No module is removed without passing the gate. | L87: M2 | M87: S | N87: High | O87: #85 | R87: Static-to-dynamic migration | S87: No
A88: 87 | B88: Claude | C88: Static-to-Dynamic Module Migration | D88: Wave 1 (pilot): base data - Department, Discipline, Team, Crew, Vendor, Tag, Instrument, EquipmentClassification | E88: Feature | F88: Not Started | G88: P0 | H88: The simplest modules; they prove the engine and become demo samples. | I88: Convert to metadata, migrate data, delete the controller/view. | J88: Eight modules run on the dynamic engine with the same permissions. | L88: M2 | M88: L | N88: Sales blocker | O88: #12 #45 #32 #86 | R88: Static-to-dynamic migration | S88: No
A89: 88 | B89: Claude | C89: Static-to-Dynamic Module Migration | D89: Wave 2: form-driven - WorkRequest, Task, Meeting, ShiftHandover, Inspection, MOC, Permit | E89: Feature | F89: Not Started | G89: P1 | H89: Form + workflow; the main benchmark of the form builder and studio. | I89: For each module build the equivalent form and workflow with the builders, migrate data, run old/new acceptance tests, then delete the static version (M_PATTERN gate). | J89: Permit to work runs with the same safety rules (LOTO/gas test). | L89: M4 | M89: XL | N89: High | O89: #87 #82 #52 | Q89: OLD-110 | R89: Static-to-dynamic migration | S89: No
A90: 89 | B90: Claude | C90: Static-to-Dynamic Module Migration | D90: Wave 3: assets and maintenance - Equipment, FunctionalLocation, Asset, MaintenancePlan, MaintenanceStrategy, WorkOrder, SparePart | E90: Feature | F90: Not Started | G90: P2 | H90: Heavy domain logic (planning, strategy); hybrid: dynamic model plus code extension. | I90: Make the asset/hierarchy models dynamic, keep planning and strategy logic as code extensions (M_SDK), measure large-list performance with QA_PERF. | J90: No performance regression on large lists. | L90: M5 | M90: XL | N90: High | O90: #88 #94 | Q90: OLD-109 | R90: Static-to-dynamic migration | S90: No
A91: 90 | B91: Claude | C91: Static-to-Dynamic Module Migration | D91: Wave 4: procurement and warehouse - Inventory, MaterialItem, MaterialRequisition, StoreRequisition, ProcurementPackage, Contract | E91: Feature | F91: Not Started | G91: P2 | H91: Shared master data with CMMS. | I91: Build the MR to procurement package to contract to receipt to store issue chain on the dynamic engine and align shared master data with INT_MASTER. | J91: MR to PO to receipt to consumption works end to end. | L91: M5 | M91: XL | N91: Medium | O91: #88 | Q91: OLD-111 | R91: Static-to-dynamic migration | S91: No
A92: 91 | B92: Claude | C92: Static-to-Dynamic Module Migration | D92: Wave 5: engineering/EDMS - DocumentRegister, Revisions, Upload, Workflow, Transmittal, TQ, DCC, VDR, MDB | E92: Feature | F92: Not Started | G92: P2 | H92: The deepest domain and a competitive advantage; only forms/workflows become dynamic, the revision engine stays static. | I92: Make EDMS forms, workflows and registers dynamic but keep the revision/transmittal engine as a specialized extension; pass revision and transmittal acceptance tests with unchanged behavior. | J92: Revision and transmittal behave exactly as before. | L92: M5 | M92: XL | N92: High | O92: #88 #94 | Q92: OLD-109 | R92: Static-to-dynamic migration | S92: No
A93: 92 | B93: Claude | C93: Static-to-Dynamic Module Migration | D93: Wave 6: production and projects - Production, ProductionOrder, ProductionRun, QC, Projects | E93: Feature | F93: Not Started | G93: P3 | H93: Lowest sales priority. | I93: After earlier waves are proven, move the production and project modules with the same pattern. | J93: Each module passed the parity gate and its static version is removed. | L93: M6 | M93: L | N93: Low | O93: #89 | R93: Static-to-dynamic migration | S93: No
A94: 93 | B94: Claude | C94: Static-to-Dynamic Module Migration | D94: Permanently static modules with extension points: AI, OCR, TableExtraction, Reliability/RCM-FMEA, Barcode, Relationship | E94: Docs | F94: Not Started | G94: P2 | H94: Specialized logic; must be callable from and composable with the dynamic engine. | I94: Document the extension contract for each. | J94: Each kept module has an extension-contract document (inputs/outputs, events, permissions) and an integration test with the dynamic engine. | L94: M5 | M94: S | N94: Medium | O94: #94 | R94: Static-to-dynamic migration | S94: No
A95: 94 | B95: Claude | C95: Static-to-Dynamic Module Migration | D95: Extension SDK (Domain Pack): custom actions, widgets, validators and views written in code inside the dynamic engine | E95: Feature | F95: Not Started | G95: P1 | H95: Without extension points every customer-specific need becomes a fork. | I95: Stable interfaces, an extension API version and signed loading. | J95: A sample extension adds a custom action to a workflow. | L95: M4 | M95: L | N95: High | O95: #10 #74 | R95: Static-to-dynamic migration | S95: No
A96: 95 | B96: User | C96: Static-to-Dynamic Module Migration | D96: Production data migration and user training (script, verification, rollback) | E96: Ops Process | F96: Not Started | G96: P1 | H96: Each wave has real data (141 existing migrations). | I96: Trial run on a copy, compare counts/hashes. | J96: For each wave: record count and hash comparison report, pre-run backup, rollback path and key-user sign-off. | L96: M4 | M96: M | N96: High | O96: #86 | R96: Static-to-dynamic migration | S96: No
A97: 96 | B97: User | C97: Licensing & Protection | D97: Licensing threat model and protection level (decided: casual-copy defense plus contract/EULA, no hardware token) | E97: Decision Needed | F97: Done | G97: P0 | H97: Owner goal: lock to machine and install time so that even a full machine image redeployed elsewhere does not work. No offline scheme is unbreakable; the aim is to defeat casual copying and back the rest with the EULA. | I97: List attack scenarios (disk image on other hardware, VM clone, snapshot restore, clock change, binary patch, licence file reuse) and for each record the defense, the residual weakness and the contractual answer. | J97: An approved ADR 'licensing threat model' with a scenario x defense x residual-risk table. | K97: Decided 2026-10-18: casual-copy defense plus contract - machine fingerprint, install seal, signed licence, restore-detection counter, code obfuscation and strong EULA. No hardware token. ADR to be written under F_ADR. ADR: plan/adr/0005-licensing-threat-model-and-vm-policy.md | L97: M0 | M97: M | N97: Sales blocker | P97: Titan #69 #207 | Q97: OLD-38 | R97: Licensing chain | S97: Yes
A98: 97 | B98: User | C98: Licensing & Protection | D98: Decision: VM/container deployment policy for licensing (decided: allowed, with extra protection) | E98: Decision Needed | F98: Done | G98: P0 | H98: Owner decision 2026-10-15: timed licences are a time period (start and end date); count-based licences are not offered. Still open: a VM or container fingerprint can be cloned, so the sales policy on VM/Docker affects how strong the anti-clone defense can be. | I98: Implement the decided policy: VMs and Docker are accepted; use a virtual TPM or hypervisor identifier where available, the restore-detection counter (L_CLONE) and a no-cloning EULA clause (L_EULA). | J98: L_FP, L_CLONE and L_EULA implement the policy; the supportability matrix lists VM and Docker as supported with these conditions. | K98: Decided 2026-10-18: VMs and Docker are allowed with extra protection (virtual TPM/hypervisor ID where available, restore-detection counter, no-cloning EULA clause). ADR: plan/adr/0005-licensing-threat-model-and-vm-policy.md | L98: M0 | M98: S | N98: High | R98: Licensing chain | S98: Yes
A99: 98 | B99: Claude | C99: Licensing & Protection | D99: Multi-signal machine fingerprint library with tolerance for small changes (Windows + Linux/Docker) | E99: Feature | F99: Not Started | G99: P0 | H99: A machine-bound licence needs a stable fingerprint. PEMS is .NET only and also ships a Docker option. | I99: Signals: motherboard UUID, CPU id, system disk serial, physical MACs, Windows MachineGuid, /etc/machine-id; weighted with a tolerance threshold (replacing one disk or NIC is allowed, three or more changed signals invalidates the licence). | J99: Test: the same machine after reboot and one NIC replaced stays valid; another machine is invalid; output is hashed (no raw serials exposed). | L99: M1 | M99: L | N99: Sales blocker | O99: #96 | P99: Titan #69 #141 | R99: Licensing chain | S99: Yes
A100: 99 | B100: Claude | C100: Licensing & Protection | D100: Install ID and install seal: install time, install key, state counter in DB and protected file | E100: Feature | F100: Not Started | G100: P0 | H100: Owner need: lock to the machine and to the install time. A random Install ID is created on first run and sealed with a local key (DPAPI/TPM where available); the licence binds to this ID and the fingerprint. | I100: Generate an install key pair, store the private key non-exportable (DPAPI machine scope or TPM), write the seal in two independent places (DB + file) and verify consistency on every start. | J100: Copying a disk/image to other hardware cannot open the seal (machine-bound key) and the app drops to 'activation required'. | L100: M1 | M100: L | N100: Sales blocker | O100: #98 | P100: Titan #64 #65 | R100: Licensing chain | S100: Yes
...

Sheet Test Plan
A1: # | B1: Backlog row | C1: Area | D1: Feature | E1: Precondition | F1: Test steps (with expected result) | G1: Risk if it fails | H1: QA Status
A2: 1 | B2: 104 | C2: Licensing & Protection | D2: Full image restored on different hardware | E2: Active install with a valid licence on machine A; machine B with different hardware | F2: 1) Take a full disk image of machine A. 2) Restore and boot it on B. 3) Open the app. Expected: 'activation required' state, no domain module opens, a suspicious-event record is logged. | G2: Risk if it fails: If it opens, copy protection is worthless and on-prem sales are unprotected. | H2: Needs QA
A3: 2 | B3: 100 | C3: Licensing & Protection | D3: Full request-to-licence cycle | E3: Fresh install with no licence | F3: 1) Open the licence page and download the .pemsreq. 2) Issue a term licence with the vendor tool. 3) Upload it. Expected: activates with the right edition/modules. 4) Upload the same licence on a second install: it must be rejected. | G3: Risk if it fails: A transferable licence means lost revenue. | H3: Needs QA
A4: 3 | B4: 105 | C4: Licensing & Protection | D4: Setting the clock back | E4: A 30-day licence with 20 days consumed | F4: Set the system clock back 20 days and start the app. Expected: soft lock/clock-tamper warning; consumed days are not restored. | G4: Risk if it fails: Unlimited free renewal. | H4: Needs QA
A5: 4 | B5: 102 | C5: Licensing & Protection | D5: Licence type boundaries | E5: A term licence expiring tonight; a lifetime licence; a trial licence | F5: 1) Let the term licence reach its end date: the app drops to restricted mode. 2) Check expiry at Jalali midnight. 3) A lifetime licence shows no expiry warning. 4) Renew a term licence before and after expiry. | G5: Risk if it fails: An off-by-one error locks a legitimate customer. | H5: Needs QA
A6: 5 | B6: 116 | C6: Licensing & Protection | D6: Hardware replacement | E6: Active install | F6: Request a re-host, vendor approves, new licence; the old licence is disabled on the old machine. Exceeding the cap requires manual approval. | G6: Risk if it fails: A legitimate customer stays down after a server failure. | H6: Needs QA
A7: 6 | B7: 110 | C7: Licensing & Protection | D7: No bypass present | E7: Final release package | F7: Scan the package for bypass flags; boot without a licence in dev/staging/prod: all three lock. The allowlisted surfaces stay open. | G7: Risk if it fails: Selling an unlocked package. | H7: Needs QA
A8: 7 | B8: 106 | C8: Licensing & Protection | D8: Issuing tool only at the vendor | E8: Customer package | F8: Open the customer package: no issuing tool and no private key exist. | G8: Risk if it fails: Exposure of licence issuing. | H8: Needs QA
A9: 8 | B9: 10 | C9: Metadata Core & Dynamic Platform | D9: Create an entity purely with metadata | E9: Clean instance | F9: Create a 'lab sample' entity with 10 fields in the UI, publish, create/edit/delete a record with no deploy. Expected: list, form, search, export and audit work. | G9: Risk if it fails: The core of dynamism does not work. | H9: Needs QA
A10: 9 | B10: 13 | C10: Metadata Core & Dynamic Platform | D10: Field type change with data | E10: Entity with 100k records | F10: Change a field from text to number: risk preview, two-step approval, backup; then roll back. Expected: data returns intact. | G10: Risk if it fails: Loss of customer data. | H10: Needs QA
A11: 10 | B11: 12 | C11: Metadata Core & Dynamic Platform | D11: Server-side paging/filter | E11: 500k records | F11: Filter and sort the list; response under 500 ms. The total count respects RLS. | G11: Risk if it fails: Repeat of a known paging regression. | H11: Needs QA
A12: 11 | B12: 178 | C12: Access, RLS, Sessions & Security | D12: Data leakage | E12: Two users with different scope | F12: Read user A's record as user B through list, search, export, report, API and AI: it must never appear. | G12: Risk if it fails: Leak of customer confidential information. | H12: Needs QA
A13: 12 | B13: 44 | C13: Dynamic Form Builder | D13: Build an inspection form | E13: Builder role | F13: Build a 20-field form with 2 tabs, a child table and conditions; preview as different roles; publish. Create a second version: old records stay intact. | G13: Risk if it fails: A failed form builder means a failed product. | H13: Needs QA
... A34: 33 | B34: 336 | C34: DevOps, Source Control & Release Management | D34: plan-sync keeps plan and the issue tracker consistent | E34: A tracker project with the Plan ID field and CI secrets. | F34: Run export and push; change a status in the issue tracker; run pull and check. Expected: workbook status follows the issue tracker, check passes; a duplicate Plan ID or Done row without evidence fails. | G34: Risk if it fails: The plan file and the issue tracker disagree and developers lose trust in one of them. | H34: Needs QA

Sheet Roadmap
A1: Epic / Milestone | B1: When | C1: Priority | D1: Areas Involved | E1: Rationale | F1: Tasks
A2: M0 - Baseline and foundation decisions | B2: Now | C2: P0 | D2: FND, LIC, BRD, DEM, WEB, MIG, CMP, QA | E2: Without the decisions on storage, UI technology, libraries, the licensing threat model and editions nothing later is stable. Decisions are cheap and unblock everything. In parallel run a real build/test and clean secrets from the repo. | F2: =COUNTIF(Backlog!$L$2:$L$350,"M0")
A3: M1 - Dynamic core, components and licensing (Alpha) | B3: Now | C3: P0 | D3: DYN, CMP, LIC, SEC, LOC | E3: These block everything else: metadata registry, dynamic API with RLS, safe schema change, grid/form, Persian/Jalali, and the whole licence chain (fingerprint, install seal, request file, signed licence, vendor tool, anti-clone). Selling without a licence and without dynamism is meaningless. | F3: =COUNTIF(Backlog!$L$2:$L$350,"M1")
A4: M2 - Builders, demo and install (Beta) | B4: Next | C4: P0 | D4: FRM, MOD, WFL, MIG, DEM, INS, BRD | E4: The form, module and workflow builders plus the first migration wave (wave 1) prove the engine works. The demo and the installer with signed updates allow sales to begin. | F4: =COUNTIF(Backlog!$L$2:$L$350,"M2")
A5: M3 - Commercial release 1.0: demo, website, brand and legal | B5: Next | C5: P1 | D5: LIC, BRD, DEM, WEB, INS, DEV, CVM, HST | E5: Sellable packaging: licence activation portal, website, sales material, pilot customer, licence upgrade/transfer/renewal and support, plus the customer registry and release process needed before the first customer is live. | F5: =COUNTIF(Backlog!$L$2:$L$350,"M3")
A6: M4 - Platform completion and module migration | B6: Next | C6: P1 | D6: DYN, CMP, FRM, MOD, WFL, MIG, SEC, INT, QA, LOC, RPT, AI, OPS, EDM, EAM | E6: Release 1.0 must be able to host every wave: the rest of the platform P1 work, wave 2, mobile, SSO, security and the report builder. | F6: =COUNTIF(Backlog!$L$2:$L$350,"M4")
A7: M5 - Competitive features (P2) | B7: Later | C7: P2 | D7: All | E7: Capabilities that make selling easier but do not block 1.0. | F7: =COUNTIF(Backlog!$L$2:$L$350,"M5")
A8: M6 - Later (P3) | B8: Later | C8: P3 | D8: All | E8: Highest uncertainty and lowest sales impact. | F8: =COUNTIF(Backlog!$L$2:$L$350,"M6")
A10: Suggested order for the first 60 days (after owner approval)
A11: Week 1: F_BASE (real build/test), F_SECRET (repo secrets), F_ADR, and the F_STORE / F_UI / F_LIBS decisions with small prototypes.
A12: Weeks 1-2: owner decisions: VM/container policy (L_TIMES), edition matrix (L_EDITION), pricing (B_PRICE), legal structure (B_ENTITY).
A13: Weeks 2-4: L_MODEL (threat model) and L_FP + L_INSTALLID (proof: an image on other hardware does not run); C_AUDIT; M_AUDIT.
A14: Weeks 3-8: vertical slice: D_OBJ + D_API + C_GRID + FRM_RUN on one sample entity (migration wave 1 pilot); S_RLS in parallel.
A15: Weeks 5-8: L_REQ -> L_LICFMT -> L_VENDOR -> L_UI -> L_FIRSTRUN (the complete licence chain) and LOC_DEFAULT / LOC_CAL.
A16: End of 60 days: an internal demo of 'build a module in the UI and run it' with the machine-locked licence working; then M2.

Sheet Sprint 1
A1: Sprint 1 - commercial and dynamic-BPMS foundation
A2: Dates | B2: 2026-10-26 to 2026-11-06 (two weeks; adjust at import)
A3: Team | B3: Member A (product owner: decisions, business, approvals), Member B (developer: reviews and merges), the AI assistant (does most Claude-doer rows under their review)
A4: Goal | B4: Record the foundation decisions, prove the component technology, start the licensing and metadata-registry designs, make the build and the demo pipeline trustworthy, and protect the source and the signing key.
A5: Why now | B5: Commercial release needs licensing and a demo; the dynamic BPMS needs the metadata registry and the component library. Both start with decisions and designs that unblock the large XL rows.
A6: Capacity rule | B6: About 11 person-weeks nominal; 11 of 16 items are doable by the assistant, so humans mainly decide, review and merge. Stretch items start only when all committed items are in review.
A7: Definition of done | B7: The row's 'Done when' text is met, evidence is written in the Report column, tests/CHANGELOG/Supportability Matrix updated (Instructions rule 22), changes merged by pull request.
A8: Out of scope | B8: Implementation of the registry (#10), the licence code (#98+), the component library build (#322+) and page migration waves: they start after these designs and the spike.
A10: Plan ID | B10: Task | C10: Owner | D10: Doer | E10: Effort | F10: Priority | G10: Committed / stretch | H10: Done when
A11: 2 | B11: Create the architecture decision record (ADR) log in plan/adr and record the decisions already taken | C11: Member A | D11: Claude | E11: S | F11: P0 | G11: Committed | H11: Done when: plan/adr contains the template and six ADRs approved by Member A; every backlog row marked decided points to its ADR.
A12: 3 | B12: Write the one-page platform operating model: what is the dynamic engine, what are Domain Packs, what stays static | C12: Member A | D12: Claude | E12: M | F12: P0 | G12: Committed | H12: Done when: Member A approved the document; every module appears in exactly one class; rows #10, #85 and #94 reference it.
A13: 107 | B13: Define and perform the licence signing-key procedure (create keys offline, storage, backup, rotation, compromise plan) | C13: Member A | D13: User | E13: M | F13: P0 | G13: Committed | H13: Done when: the procedure is approved and followed; the public key is in the repository; a test signature verifies; the private key is not on any development machine.
A14: 257 | B14: Move the source code to a private company-owned GitHub organization with access control, branch protection and a backup | C14: Member A | D14: User | E14: M | F14: P0 | G14: Committed | H14: Done when: the repository is private; branch protection and 2FA are on; a backup job ran once; the member list with roles is recorded.
A15: 337 | B15: Finish the issue-tracker setup: board columns, Plan ID field, and the API token stored as a CI secret | C15: Member A | D15: User | E15: S | F15: P0 | G15: Committed | H15: Done when: a test import of the generated import file (python tools/plan-sync/plan_sync.py export) creates the epics and issues with Plan IDs and the Sprint 1 items; the bot token works from CI.
A16: 338 | B16: Design the metadata registry (apps, modules, entities, fields, relations, versions) and write the ADR | C16: Member A | D16: Claude | E16: M | F16: P0 | G16: Committed | H16: Done when: the design document and ADR exist; Member A and Member B have reviewed them; the sketched classes compile; open questions are listed with an owner; rows #10, #11, #13 and #28 reference the document.
A17: 339 | B17: Write the licensing technical design: machine fingerprint signals, install seal, request and licence file formats, verification points, vendor tool | C17: Member A | D17: Claude | E17: M | F17: P0 | G17: Committed | H17: Done when: the document covers rows #98-#106 with data formats and a sequence for first activation, renewal and restore-from-image; Member A approved it; each open risk names the contractual answer (EULA, #120).
A18: 1 | B18: Run the build and test suite once and store a baseline report (counts, duration, environment, every failing test) | C18: Member B | D18: Claude | E18: S | F18: P0 | G18: Committed | H18: Done when: plan/baseline/<date>.md exists with the numbers above; each failing test is listed with a cause; each real defect has its own backlog row. Known today (not yet in a report): LinuxDeploymentArtifactsTests LF check, a SQLEXPRESS-only sidebar test and ImportCenterNavigationTests (LetterCompose) fail on a clean main.
A19: 7 | B19: Make the build workflow fail on red tests and publish a versioned artifact on version tags | C19: Member B | D19: Claude | E19: M | F19: P0 | G19: Committed | H19: Done when: a red test fails the workflow; a tag produces a release artifact with version, commit and build number; no secret is stored in the repository.
A20: 9 | B20: Audit the repository, history and container files for secrets and unsafe defaults, and fix what remains | C20: Member B | D20: Claude | E20: S | F20: P0 | G20: Committed | H20: Done when: the report exists; HEAD is clean; every historical finding has a decision and an owner.
A21: 29 | B21: Finish the UI pattern audit: review the 30 heaviest pages by hand and compute the convertible percentage per migration wave | C21: Member B | D21: Claude | E21: M | F21: P0 | G21: Committed | H21: Done when: the audit document lists A/B/C for 30 pages and the percentage per wave W1-W5; the list of missing components feeds rows #322-#325.
A22: 30 | B22: Consolidate the design tokens into one file and remove hard-coded colours from the shared CSS | C22: Member B | D22: Claude | E22: M | F22: P0 | G22: Committed | H22: Done when: the four listed CSS files contain no hex colours and no physical left/right rules; screenshots show no visible change; the token file is documented in docs/design/WORKSPACE_DESIGN_SYSTEM.md.
... A27: 340 | B27: Make the demo site start: issue the TLS certificate and diagnose why the application does not answer after the first deploy | C27: Member B | D27: Claude | E27: M | F27: P0 | G27: Committed | H27: Done when: https://demo.parmisata.ir opens with a valid certificate; /health/database returns UpToDate; the demo workflow run is green end to end; the cause and fix are written in docs/deployment/DEMO_DEPLOYMENT.md.

Sheet Licensing Design
A1: PEMS licensing design - machine and install-time locked (on-prem, offline)
A2: Owner need: even if a whole machine is imaged and deployed elsewhere it must not work; a file is generated on the customer server, returned to us, and we deliver the real licence; lifetime or timed. Limits: no offline scheme is unbreakable - the goal is to defeat casual copying and add contractual backing.
A4: Step | B4: Stage | C4: Description | D4: Backlog rows
A5: 1 | B5: Install | C5: The installer runs; first start creates a random Install ID and a key pair; the private key is made non-exportable with DPAPI/TPM; install time and a monotonic counter are written to the 'install seal' (DB + an independent file). | D5: #99
A6: 2 | B6: Request | C6: Without a licence the system starts in 'activation required' mode and creates a .pemsreq file: hashed fingerprint, Install ID, install time, version, customer id, nonce, install-key signature. | D6: #98 #100 #108
A7: 3 | B7: Return to vendor | C7: The customer gives the file to us through the website portal (WEB_ACT) or by hand; the product itself never calls out. | D7: #161 #123
A8: 4 | B8: Issue | C8: The vendor tool (L_VENDOR) validates the signature and structure, selects edition/modules/limits/type (lifetime or term) and signs a .pemslic with the offline private key; the licence is bound to the nonce, Install ID and fingerprint hash of that request. | D8: #101 #102 #106 #107
A9: 5 | B9: Activate | C9: The customer uploads the licence (or a zip); verification: signature, Install ID match, fingerprint, seal, monotonic counter, expiry; then an automatic restart. | D9: #103 #108
A10: 6 | B10: Operate | C10: Multiple checks at startup/periodic/sensitive operations; expiry warnings for term licences; failure means restricted read-only mode, not a crash. | D10: #103 #105 #115
A11: 7 | B11: Renew/transfer | C11: Renewal with a small file; hardware replacement with a new request and revocation of the old licence (re-host) with a cap on count. | D11: #115 #116 #117
A13: Threat and defense table
A14: # | B14: Attack scenario | C14: Defense | D14: Residual risk | E14: Rows
A15: 1 | B15: Full machine image on different hardware | C15: Multi-signal fingerprint plus a non-exportable install key (DPAPI/TPM); the seal cannot be opened | D15: Low | E15: #98 #99
A16: 2 | B16: VM clone (same virtual hardware appearance) | C16: VM/container policy (L_TIMES); virtual TPM / hypervisor identifiers; monotonic counter and lifecycle trail | D16: Medium - needs a commercial decision and contract | E16: #97 #104 #120
A17: 3 | B17: Restoring an old snapshot on the same machine | C17: Monotonic counter plus audit hash chain; a lower counter is suspicious; re-activation required | D17: Medium | E17: #104
A18: 4 | B18: Setting the clock back for a term licence | C18: Sealed last-seen time; a jump back causes a soft lock | D18: Low | E18: #105
A19: 5 | B19: Binary patch / removing the licence check | C19: Several independent checks, obfuscation, assembly signing, integrity checks | D19: Medium (no software defense is absolute) | E19: #103 #118
A20: 6 | B20: Copying or sharing a licence file between customers | C20: The licence is bound to Install ID + fingerprint + nonce; another install rejects it | D20: Low | E20: #101
A21: 7 | B21: Leak of the private signing key | C21: Offline key/HSM, two-person control, public-key rotation via update | D21: Critical if it happens | E21: #107
A22: 8 | B22: Licence issuing tool inside the customer package | C22: Two flags (build-time/run-time); package allowlist scan | D22: Low | E22: #106 #119
A23: 9 | B23: Leftover bypass from development | C23: No bypass flag; a signed dev licence; release test | D23: Low | E23: #110
A24: 10 | B24: Recovery after hardware failure (legitimate user, new machine) | C24: Official re-host path with vendor approval and a cap on count | D24: Operational | E24: #116 #171

Sheet Capability Checklist
A1: # | B1: Area | C1: Capability | D1: Reference | E1: PEMS today | F1: PEMS rows | G1: Target | H1: Parity
A2: 1 | B2: RBAC and authorization | C2: One engine for roles/groups/rules/users plus row-level relevance | D2: Titan #1 #5 | E2: Partial - AccessControlService, RoleAssignment | F2: #178 #180 | G2: Better | H2: Open
A3: 2 | B3: RBAC and authorization | C3: Editable permission matrix on unit and user forms | D3: Titan #3 | E3: Missing | F3: #60 | G3: Equal | H3: Open
A4: 3 | B4: RBAC and authorization | C4: Bulk permission operations (clear/add owner) | D4: Titan #2 | E4: Missing | F4: #60 | G4: Equal | H4: Open
A5: 4 | B5: Sessions and security | C5: Session registry, split TTLs, force-logout | D5: Titan #67 #104 | E5: Missing (plain cookie) | F5: #182 | G5: Better | H5: Open
A6: 5 | B6: Sessions and security | C6: Superadmin TOTP | D6: Titan #67 | E6: FIDO2 (stronger) | F6: #241 | G6: Better | H6: Open
A7: 6 | B7: Sessions and security | C7: AES-GCM field encryption with a machine key | D7: Titan #64 | E7: Missing | F7: #188 | G7: Equal | H7: Open
A8: 7 | B8: Licensing | C8: Offline machine-locked Ed25519 licence | D8: Titan #69 #131 | E8: Missing | F8: #101 #98 | G8: Better (install seal + anti-clone) | H8: Open
A9: 8 | B9: Licensing | C9: Model/module-level licence | D9: Titan #70 #168 | E9: Missing | F9: #113 | G9: Equal | H9: Open
A10: 9 | B10: Licensing | C10: Zip upload, fingerprint display, automatic restart | D10: Titan #140 #141 #146 | E10: Missing | F10: #108 | G10: Equal | H10: Open
A11: 10 | B11: Licensing | C11: Web-based superowner issuing tool | D11: Titan #145 | E11: Missing | F11: #106 | G11: Equal | H11: Open
A12: 11 | B12: Licensing | C12: Signed update package and Update page | D12: Titan #249 | E12: Missing | F12: #170 | G12: Equal | H12: Open
A13: 12 | B13: Licensing | C13: Code protection (bytecode) | D13: Titan #71 | E13: Missing | F13: #118 | G13: Equal | H13: Open
... A37: 36 | B37: Hosting | C37: PHP-fronted mode / MySQL | D37: Titan #147 #148 | E37: N/A - .NET + SQL Server | F37: - | G37: N/A by design | H37: Open
B40: Rule: capabilities PEMS must offer, sourced from the reference platform (see the Reference column). When every row is Parity/Better/N/A and the acceptance tests pass, the owner decides whether PEMS replaces it.

Sheet Lessons
A1: Project memory - facts and lessons
A3: - | B3: PEMS is a brand-new project. Its task source of truth is this workbook (plan/PEMS_Backlog_Roadmap.xlsx).
A4: - | B4: Repository: PEMS-cmms-edit-empoleeys-master (public GitHub under a personal account - ownership/licence to be clarified, row B_ENTITY). Stack: .NET 10, EF Core 10, SQL Server, Hangfire, QuestPDF, Fido2, Serilog, Ollama.
A5: - | B5: Working language of the product is Persian. The app's default culture is currently en and the calendar is deliberately Gregorian (Program.cs) - rows LOC_DEFAULT and LOC_CAL.
A6: - | B6: Licensing: on-prem, machine + install-time lock; request/licence file process; lifetime or term (a time period); product name is PEMS (decided).
A7: - | B7: Old audit workbooks are kept in '0 - trash'; the previous Persian edition of this workbook is kept there too.
A8: - | B8: Not yet done as of 2026-10-15: build/test run, licensing, installer, builders.
A10: # | B10: Lesson | C10: Reference | D10: Explanation | E10: PEMS rows
A11: 1 | B11: Registry-driven, not code-driven | C11: Titan Overview | D11: Apps/models/fields/statuses/licences are database rows and one generic CRUD/export/import engine runs them; adding an app means seeding metadata. | E11: #10 #12
A12: 2 | B12: A registry change must not require a rebuild | C12: Titan #61 | D12: A static export forced a full rebuild and redeploy after each registry change; PEMS is server-rendered but must keep this property. | E12: #28
A13: 3 | B13: Registry cache + ETag + gzip | C13: Titan #50 | D13: Database slowness was fixed by caching the metadata registry and conditional GET; build it in from the start. | E13: #28
A14: 4 | B14: One contract for server-side paging | C14: Titan #49 #136 | D14: It stayed incomplete twice; use one query contract and one grid, not patch by patch. | E14: #12 #32
A15: 5 | B15: Changing a field type on live data is the riskiest operation | C15: Titan #17 | D15: Needs guided ALTER, rollback and a data-risk warning. | E15: #13
A16: 6 | B16: Licence was enforced only in production | C16: Titan #143 #204 | D16: Staging/local booted without a licence, and a LICENSE_BYPASS flag was left behind. | E16: #110
A17: 7 | B17: The first-run licence flow was fragile | C17: Titan #142 #144 | D17: The setup token was not created in one case; the rate limiter was tied to the DB and requests hung. | E17: #109
A18: 8 | B18: Offer the fingerprint in the UI, not the terminal | C18: Titan #141 | D18: Copy/download of the fingerprint from the page; delivery as zip and automatic restart. | E18: #108 #100
A19: 9 | B19: Licence issuing in a separate tool, never in the customer package | C19: Titan #145 | D19: Two flags (build/run); the superowner tool stays with the vendor. | E19: #106 #119
A20: 10 | B20: Public surfaces must not need a licence | C20: Titan #163 #168 | D20: An explicit allowlist; app licensing derived from model licences. | E20: #111
A21: 11 | B21: Signing keys are a permanent operational responsibility | C21: Titan #207 | D21: A key procedure is needed, not just code. | E21: #107
A22: 12 | B22: Package allowlist for releases | C22: Titan #68 #137 | D22: Secrets and development files remained in the package; allowlist scan. | E22: #119 #9
... A39: 29 | B39: One owner per field between the plan file and the issue tracker | C39: PEMS (2026-10-23) | D39: Two systems drift unless each field has a single owner and a script compares them. Plan ID and issue key link the records; the tracker owns status, the workbook owns scope; changes to the workbook go through pull requests. | E39: #335 #336

Sheet Supportability Matrix
A1: Supportability Matrix - what PEMS supports, and up to which limits
A2: Created 2026-10-18 by owner instruction. Update it in every finished task (Instructions rule). Builder limits and all supported values come from here. Status: Planned, Decided, Supported, Supported (unverified), TBD (to be measured), Deprecated, Not supported.
A4: ID | B4: Category | C4: Capability / limit | D4: Component | E4: Supported value / limit | F4: Applies from version | G4: Status | H4: Verified by (backlog rows) | I4: Notes
A5: SM-01 | B5: Deployment | C5: Physical Windows Server | D5: Core / installer | E5: Supported platform; exact Windows Server versions to be fixed by the environment validator. | F5: - | G5: Planned | H5: #167 #168 #98
A6: SM-02 | B6: Deployment | C6: Virtual machines (VMware, Hyper-V, Proxmox) | D6: Core | E6: Allowed. Licence uses a virtual TPM or hypervisor identifier where available plus the restore-detection counter; EULA forbids cloning. | F6: - | G6: Decided | H6: #97 #104 #120 | I6: Decision 2026-10-18.
A7: SM-03 | B7: Deployment | C7: Docker containers | D7: Core | E7: Allowed with the same extra protection; production hardening pending. | F7: - | G7: Decided | H7: #172 #104 | I7: Decision 2026-10-18.
A8: SM-04 | B8: Deployment | C8: Offline operation (no internet) | D8: Core | E8: Required: no CDN, no outbound calls from the product. | F8: - | G8: Planned | H8: #42
A9: SM-05 | B9: Database | C9: SQL Server versions | D9: Core | E9: TBD - fixed by the first real build/test run and the environment validator. | F9: - | G9: TBD | H9: #1 #168
A10: SM-06 | B10: Database | C10: Upgrade path | D10: Core | E10: Upgrade from any supported release; target is N-2. | F10: - | G10: Planned | H10: #262 #274
A11: SM-07 | B11: Licence | C11: Licence types | D11: Core | E11: Lifetime and term (a time period), plus trial and demo. No count-based licences. | F11: - | G11: Decided | H11: #102 | I11: Decision 2026-10-15.
A12: SM-08 | B12: Licence | C12: User limit | D12: Core | E12: No licence limit on users. | F12: - | G12: Decided | H12: - | I12: Decision 2026-10-18; user metering cancelled.
A13: SM-09 | B13: Licence | C13: Maintenance | D13: Core | E13: Perpetual licence plus annual maintenance; maintenance controls which updates can be installed. | F13: - | G13: Planned | H13: #275 #130 | I13: Decision 2026-10-18.
A14: SM-10 | B14: Versioning | C14: Product version | D14: Core | E14: The installed product version is the core version. | F14: - | G14: Planned | H14: #269 #282 | I14: Decision 2026-10-18.
A15: SM-11 | B15: Versioning | C15: Module versions | D15: Module | E15: Each module has its own version and a declared compatible core range. | F15: - | G15: Planned | H15: #282 #283 #284 | I15: Decision 2026-10-18.
A16: SM-12 | B16: Builders | C16: Custom modules per instance | D16: Core | E16: TBD - set from measured limits. | F16: - | G16: TBD | H16: #281 #66
A17: SM-13 | B17: Builders | C17: Forms per module | D17: Core | E17: TBD - set from measured limits. | F17: - | G17: TBD | H17: #281 #66
A18: SM-14 | B18: Builders | C18: Fields per entity | D18: Core | E18: TBD - set from measured limits. | F18: - | G18: TBD | H18: #281 #11
A19: SM-15 | B19: Builders | C19: Workflows and stages per workflow | D19: Core | E19: TBD - set from measured limits. | F19: - | G19: TBD | H19: #281 #67
A20: SM-16 | B20: Builders | C20: Child-table rows per form | D20: Core | E20: TBD; target 200 rows without slowness. | F20: - | G20: TBD | H20: #281 #48
A21: SM-17 | B21: Data volume | C21: Records per entity with filter and sort under 500 ms | D21: Core | E21: Target 500,000 records. | F21: - | G21: Planned | H21: #12 #202
A22: SM-18 | B22: Concurrency | C22: Concurrent users tested | D22: Core | E22: TBD from the performance suite; not limited by the licence. | F22: - | G22: TBD | H22: #202
A23: SM-19 | B23: Localization | C23: Persian RTL default, English optional | D23: Core | E23: Planned; current default culture is English. | F23: - | G23: Planned | H23: #205
A24: SM-20 | B24: Localization | C24: Calendars | D24: Core | E24: Jalali and Gregorian; stored as Gregorian/UTC. | F24: - | G24: Planned | H24: #206
A25: SM-21 | B25: Clients | C25: Supported browsers | D25: Core | E25: TBD - set with the responsive QA matrix. | F25: - | G25: TBD | H25: #39
A26: SM-22 | B26: Clients | C26: Offline mobile work execution | D26: Module | E26: Planned; not yet supported. | F26: - | G26: Planned | H26: #223
A27: SM-23 | B27: Security | C27: Authentication | D27: Core | E27: ASP.NET Identity with lockout and WebAuthn/FIDO2 step-up (estimated from code). | F27: - | G27: Supported (unverified) | H27: #240 #241 | I27: Acceptance tests not run.
A28: SM-24 | B28: Domain | C28: Existing modules: EDMS/VDR, CMMS, permit to work, inventory, production | D28: Modules | E28: Present as static modules (estimated from code). | F28: - | G28: Supported (unverified) | H28: #250 #244 | I28: Acceptance tests not run.
A29: SM-25 | B29: AI | C29: Local AI (Ollama, OCR, semantic search) | D29: Module | E29: Present (estimated from code). | F29: - | G29: Supported (unverified) | H29: #248 | I29: Acceptance tests not run.
A30: SM-26 | B30: Deployment | C30: Database install (first run) and update (later runs) | D30: Core / startup | E30: Fully code-first on SQL Server: the database is created if missing, an empty database is installed and an existing one is updated by EF Core migrations at startup or from Admin > Database Update; full-text search is a migration (install the SQL Server Full-Text feature BEFORE the first run). Switch off the automatic run with Database:MigrateOnStartup=false. | F30: - | G30: Supported (unverified) | H30: #309 #310 #167 #262 | I30: Verified on SQL Server LocalDB (install, update, unmanaged schema, full app start). Not yet verified on the demo host or on SQL Server with Full-Text.
A31: SM-27 | B31: Deployment | C31: Schema state inspection | D31: Core / Admin | E31: Admin > System Monitoring > Database Update (SystemAdmin) and anonymous GET /health/database (200 only when UpToDate). | F31: - | G31: Supported (unverified) | H31: #310 #312 | I31: Page access control checked (anonymous redirected to login); not yet viewed as admin in a browser.
A32: SM-28 | B32: Deployment | C32: Database restored without migration history | D32: Core | E32: Reported as 'Unmanaged schema' and never modified automatically; a baseline tool is planned. | F32: - | G32: Planned | H32: #310 #313 | I32: Detection is tested; adoption is not supported yet.
A33: SM-29 | B33: Branding | C33: Release notes on the login page | D33: Core / login | E33: Planned: bilingual, offline release notes of the installed release shown to anonymous visitors. | F33: - | G33: Planned | H33: #314 | I33: Not started.
A34: SM-30 | B34: Deployment | C34: Configuration and secrets | D34: Core | E34: Settings in env/<name>.env and secrets in env/<name>.secrets.env for local, docker, demo, uat and production-kangan; PEMS_ENV selects the environment; real environment variables override; required settings fail fast; appsettings.json is empty. | F34: - | G34: Supported (unverified) | H34: #315 #316 | I34: Verified on a developer machine (LocalDB). Demo pipeline, Docker and the Linux VM kit not yet exercised.
A35: SM-31 | B35: UI | C35: Reusable UI components (PEMS.UI) | D35: PEMS.UI | E35: Planned: every field, table, badge, skeleton, modal and page template is a component rendered from descriptors; RTL/LTR, offline, tokens only. | F35: - | G35: Planned | H35: #319-#334 | I35: Audit baseline recorded 2026-10-23; no component exists yet.
A36: SM-32 | B36: Delivery | C36: Plan workbook <-> the issue tracker consistency | D36: tools/plan-sync | E36: Export of the backlog to tracker CSV and an offline consistency check; push/pull planned. | F36: - | G36: Planned | H36: #335 #336 #337 | I36: Export and check verified on the workbook; the issue tracker side not set up.
A37: SM-33 | B37: Delivery | C37: Schema migrations deployed separately from the data layer | D37: PEMS.Migrations / PEMS.Persistence | E37: Migrations, snapshot and design-time factory live in PEMS.Migrations; a data-layer-only change leaves PEMS.Migrations.dll byte-identical (build with DebugType=none), so the difference upload skips it | F37: - | G37: Done | H37: #354 #351 | I37: Add a migration with the --project PEMS.Migrations option. Verified 2026-10-25: Persistence 29 MB -> 6 MB, Migrations 23 MB.
A38: SM-34 | B38: Deployment | C38: Pre-production staging environment | D38: Core / deploy pipeline | E38: staging branch -> staging subdomain, own database, env/staging.env, STAGING_* secrets; same reusable pipeline as demo | F38: - | G38: Done | H38: #351 | I38: Verified 2026-10-25 (run 40208748572).
... A48: SM-44 | B48: UI | C48: List page component (frame, toolbar, filters, KPIs on demand, chips, grid) | D48: PEMS.UI (pems-list-* tag helpers, pems-list.css/js) | E48: One component for record list pages: full-window table with sticky header and bottom pager, one icon toolbar (search over the title with the shared autocomplete, filters dropdown with count badge, KPI row on demand remembered per browser, Excel, reset columns, New), removable filter chips, empty state with clear-all. Each page keeps its own columns, filters, actions and permissions. In use: Engineering Documents, VDR (wave 0). | F48: - | G48: Partial | H48: SCRUM-337 | I48: Waves W1-W4 (document control, CMMS, warehouse/procurement, admin) still to move. Saved views, column picker, pinning and virtualization are SCRUM-54.

Sheet Old to New Map
A1: Old row | B1: Old epic | C1: Old title | D1: Old priority | E1: Old status | F1: Outcome | G1: New rows | H1: Note
A2: OLD-1 | B2: E0 | C2: Run official build and test baseline | D2: P0 | E2: Not Started | F2: Rewritten | G2: #1
A3: OLD-2 | B3: E0 | C3: Create architecture decision log | D3: P0 | E3: Not Started | F3: Rewritten | G3: #2
A4: OLD-3 | B4: E1 | C4: Define platform operating model | D4: P0 | E4: Not Started | F4: Rewritten | G4: #3
A5: OLD-4 | B5: E1 | C5: Build app/module registry | D5: P0 | E5: Not Started | F5: Merged | G5: #10
A6: OLD-5 | B6: E1 | C6: Build entity registry | D6: P0 | E6: Not Started | F6: Merged | G6: #10
A7: OLD-6 | B7: E1 | C7: Add metadata versioning | D7: P0 | E7: Not Started | F7: Split | G7: #10 #69
A8: OLD-7 | B8: E1 | C8: Generate menus from metadata | D8: P1 | E8: Not Started | F8: Rewritten | G8: #20
A9: OLD-8 | B9: E2 | C9: Build form designer | D9: P0 | E9: Not Started | F9: Rewritten | G9: #44
A10: OLD-9 | B10: E2 | C10: Build form runtime | D10: P0 | E10: Not Started | F10: Rewritten | G10: #45
A11: OLD-10 | B11: E2 | C11: Add validation rule builder | D11: P0 | E11: Not Started | F11: Rewritten | G11: #46
A12: OLD-11 | B12: E2 | C12: Add conditional visibility/editability | D12: P0 | E12: Not Started | F12: Rewritten | G12: #47
A13: OLD-12 | B13: E2 | C13: Add field-level security | D13: P1 | E13: Not Started | F13: Split | G13: #50 #181
... A131: OLD-D18 | B131: D10 | C131: Domain module breadth exists | D131: P0 | E131: Done | F131: Recorded as Done | G131: #250

Sheet Summary
A1: Automatic summary (formulas over the Backlog sheet)
A3: Total tasks | B3: =COUNTA(Backlog!$D$2:$D$350)
A4: Owner tasks (Doer = User) | B4: =COUNTIF(Backlog!$B$2:$B$350,"User")
A6: Status x priority
A7: Status | B7: P0 | C7: P1 | D7: P2 | E7: P3 | F7: Total
A8: Not Started | B8: =COUNTIFS(Backlog!$F$2:$F$350,$A8,Backlog!$G$2:$G$350,"P0") | C8: =COUNTIFS(Backlog!$F$2:$F$350,$A8,Backlog!$G$2:$G$350,"P1") | D8: =COUNTIFS(Backlog!$F$2:$F$350,$A8,Backlog!$G$2:$G$350,"P2") | E8: =COUNTIFS(Backlog!$F$2:$F$350,$A8,Backlog!$G$2:$G$350,"P3") | F8: =SUM(B8:E8)
A9: In Progress | B9: =COUNTIFS(Backlog!$F$2:$F$350,$A9,Backlog!$G$2:$G$350,"P0") | C9: =COUNTIFS(Backlog!$F$2:$F$350,$A9,Backlog!$G$2:$G$350,"P1") | D9: =COUNTIFS(Backlog!$F$2:$F$350,$A9,Backlog!$G$2:$G$350,"P2") | E9: =COUNTIFS(Backlog!$F$2:$F$350,$A9,Backlog!$G$2:$G$350,"P3") | F9: =SUM(B9:E9)
A10: Partial | B10: =COUNTIFS(Backlog!$F$2:$F$350,$A10,Backlog!$G$2:$G$350,"P0") | C10: =COUNTIFS(Backlog!$F$2:$F$350,$A10,Backlog!$G$2:$G$350,"P1") | D10: =COUNTIFS(Backlog!$F$2:$F$350,$A10,Backlog!$G$2:$G$350,"P2") | E10: =COUNTIFS(Backlog!$F$2:$F$350,$A10,Backlog!$G$2:$G$350,"P3") | F10: =SUM(B10:E10)
A11: Done | B11: =COUNTIFS(Backlog!$F$2:$F$350,$A11,Backlog!$G$2:$G$350,"P0") | C11: =COUNTIFS(Backlog!$F$2:$F$350,$A11,Backlog!$G$2:$G$350,"P1") | D11: =COUNTIFS(Backlog!$F$2:$F$350,$A11,Backlog!$G$2:$G$350,"P2") | E11: =COUNTIFS(Backlog!$F$2:$F$350,$A11,Backlog!$G$2:$G$350,"P3") | F11: =SUM(B11:E11)
A12: Hold | B12: =COUNTIFS(Backlog!$F$2:$F$350,$A12,Backlog!$G$2:$G$350,"P0") | C12: =COUNTIFS(Backlog!$F$2:$F$350,$A12,Backlog!$G$2:$G$350,"P1") | D12: =COUNTIFS(Backlog!$F$2:$F$350,$A12,Backlog!$G$2:$G$350,"P2") | E12: =COUNTIFS(Backlog!$F$2:$F$350,$A12,Backlog!$G$2:$G$350,"P3") | F12: =SUM(B12:E12)
A13: Later | B13: =COUNTIFS(Backlog!$F$2:$F$350,$A13,Backlog!$G$2:$G$350,"P0") | C13: =COUNTIFS(Backlog!$F$2:$F$350,$A13,Backlog!$G$2:$G$350,"P1") | D13: =COUNTIFS(Backlog!$F$2:$F$350,$A13,Backlog!$G$2:$G$350,"P2") | E13: =COUNTIFS(Backlog!$F$2:$F$350,$A13,Backlog!$G$2:$G$350,"P3") | F13: =SUM(B13:E13)
A14: Cancelled | B14: =COUNTIFS(Backlog!$F$2:$F$350,$A14,Backlog!$G$2:$G$350,"P0") | C14: =COUNTIFS(Backlog!$F$2:$F$350,$A14,Backlog!$G$2:$G$350,"P1") | D14: =COUNTIFS(Backlog!$F$2:$F$350,$A14,Backlog!$G$2:$G$350,"P2") | E14: =COUNTIFS(Backlog!$F$2:$F$350,$A14,Backlog!$G$2:$G$350,"P3") | F14: =SUM(B14:E14)
A15: Obsolete | B15: =COUNTIFS(Backlog!$F$2:$F$350,$A15,Backlog!$G$2:$G$350,"P0") | C15: =COUNTIFS(Backlog!$F$2:$F$350,$A15,Backlog!$G$2:$G$350,"P1") | D15: =COUNTIFS(Backlog!$F$2:$F$350,$A15,Backlog!$G$2:$G$350,"P2") | E15: =COUNTIFS(Backlog!$F$2:$F$350,$A15,Backlog!$G$2:$G$350,"P3") | F15: =SUM(B15:E15)
A16: Total | B16: =SUM(B8:B15) | C16: =SUM(C8:C15) | D16: =SUM(D8:D15) | E16: =SUM(E8:E15) | F16: =SUM(F8:F15)
A18: Area x priority (remaining = not Done/Later/Cancelled/Obsolete)
A19: Area | B19: Total | C19: P0 | D19: P1 | E19: P2 | F19: P3 | G19: Remaining | H19: Done
A20: Foundation, Architecture Decisions & Baseline | B20: =COUNTIF(Backlog!$C$2:$C$350,$A20) | C20: =COUNTIFS(Backlog!$C$2:$C$350,$A20,Backlog!$G$2:$G$350,"P0") | D20: =COUNTIFS(Backlog!$C$2:$C$350,$A20,Backlog!$G$2:$G$350,"P1") | E20: =COUNTIFS(Backlog!$C$2:$C$350,$A20,Backlog!$G$2:$G$350,"P2") | F20: =COUNTIFS(Backlog!$C$2:$C$350,$A20,Backlog!$G$2:$G$350,"P3") | G20: =B20-H20-COUNTIFS(Backlog!$C$2:$C$350,$A20,Backlog!$F$2:$F$350,"Cancelled")-COUNTIFS(Backlog!$C$2:$C$350,$A20,Backlog!$F$2:$F$350,"Obsolete")-COUNTIFS(Backlog!$C$2:$C$350,$A20,Backlog!$F$2:$F$350,"Later") | H20: =COUNTIFS(Backlog!$C$2:$C$350,$A20,Backlog!$F$2:$F$350,"Done")
A21: Metadata Core & Dynamic Platform | B21: =COUNTIF(Backlog!$C$2:$C$350,$A21) | C21: =COUNTIFS(Backlog!$C$2:$C$350,$A21,Backlog!$G$2:$G$350,"P0") | D21: =COUNTIFS(Backlog!$C$2:$C$350,$A21,Backlog!$G$2:$G$350,"P1") | E21: =COUNTIFS(Backlog!$C$2:$C$350,$A21,Backlog!$G$2:$G$350,"P2") | F21: =COUNTIFS(Backlog!$C$2:$C$350,$A21,Backlog!$G$2:$G$350,"P3") | G21: =B21-H21-COUNTIFS(Backlog!$C$2:$C$350,$A21,Backlog!$F$2:$F$350,"Cancelled")-COUNTIFS(Backlog!$C$2:$C$350,$A21,Backlog!$F$2:$F$350,"Obsolete")-COUNTIFS(Backlog!$C$2:$C$350,$A21,Backlog!$F$2:$F$350,"Later") | H21: =COUNTIFS(Backlog!$C$2:$C$350,$A21,Backlog!$F$2:$F$350,"Done")
A22: Component Library & Design System | B22: =COUNTIF(Backlog!$C$2:$C$350,$A22) | C22: =COUNTIFS(Backlog!$C$2:$C$350,$A22,Backlog!$G$2:$G$350,"P0") | D22: =COUNTIFS(Backlog!$C$2:$C$350,$A22,Backlog!$G$2:$G$350,"P1") | E22: =COUNTIFS(Backlog!$C$2:$C$350,$A22,Backlog!$G$2:$G$350,"P2") | F22: =COUNTIFS(Backlog!$C$2:$C$350,$A22,Backlog!$G$2:$G$350,"P3") | G22: =B22-H22-COUNTIFS(Backlog!$C$2:$C$350,$A22,Backlog!$F$2:$F$350,"Cancelled")-COUNTIFS(Backlog!$C$2:$C$350,$A22,Backlog!$F$2:$F$350,"Obsolete")-COUNTIFS(Backlog!$C$2:$C$350,$A22,Backlog!$F$2:$F$350,"Later") | H22: =COUNTIFS(Backlog!$C$2:$C$350,$A22,Backlog!$F$2:$F$350,"Done")
A23: Dynamic Form Builder | B23: =COUNTIF(Backlog!$C$2:$C$350,$A23) | C23: =COUNTIFS(Backlog!$C$2:$C$350,$A23,Backlog!$G$2:$G$350,"P0") | D23: =COUNTIFS(Backlog!$C$2:$C$350,$A23,Backlog!$G$2:$G$350,"P1") | E23: =COUNTIFS(Backlog!$C$2:$C$350,$A23,Backlog!$G$2:$G$350,"P2") | F23: =COUNTIFS(Backlog!$C$2:$C$350,$A23,Backlog!$G$2:$G$350,"P3") | G23: =B23-H23-COUNTIFS(Backlog!$C$2:$C$350,$A23,Backlog!$F$2:$F$350,"Cancelled")-COUNTIFS(Backlog!$C$2:$C$350,$A23,Backlog!$F$2:$F$350,"Obsolete")-COUNTIFS(Backlog!$C$2:$C$350,$A23,Backlog!$F$2:$F$350,"Later") | H23: =COUNTIFS(Backlog!$C$2:$C$350,$A23,Backlog!$F$2:$F$350,"Done")
A24: Dynamic Module Builder | B24: =COUNTIF(Backlog!$C$2:$C$350,$A24) | C24: =COUNTIFS(Backlog!$C$2:$C$350,$A24,Backlog!$G$2:$G$350,"P0") | D24: =COUNTIFS(Backlog!$C$2:$C$350,$A24,Backlog!$G$2:$G$350,"P1") | E24: =COUNTIFS(Backlog!$C$2:$C$350,$A24,Backlog!$G$2:$G$350,"P2") | F24: =COUNTIFS(Backlog!$C$2:$C$350,$A24,Backlog!$G$2:$G$350,"P3") | G24: =B24-H24-COUNTIFS(Backlog!$C$2:$C$350,$A24,Backlog!$F$2:$F$350,"Cancelled")-COUNTIFS(Backlog!$C$2:$C$350,$A24,Backlog!$F$2:$F$350,"Obsolete")-COUNTIFS(Backlog!$C$2:$C$350,$A24,Backlog!$F$2:$F$350,"Later") | H24: =COUNTIFS(Backlog!$C$2:$C$350,$A24,Backlog!$F$2:$F$350,"Done")
A25: Workflow Studio & BPMS | B25: =COUNTIF(Backlog!$C$2:$C$350,$A25) | C25: =COUNTIFS(Backlog!$C$2:$C$350,$A25,Backlog!$G$2:$G$350,"P0") | D25: =COUNTIFS(Backlog!$C$2:$C$350,$A25,Backlog!$G$2:$G$350,"P1") | E25: =COUNTIFS(Backlog!$C$2:$C$350,$A25,Backlog!$G$2:$G$350,"P2") | F25: =COUNTIFS(Backlog!$C$2:$C$350,$A25,Backlog!$G$2:$G$350,"P3") | G25: =B25-H25-COUNTIFS(Backlog!$C$2:$C$350,$A25,Backlog!$F$2:$F$350,"Cancelled")-COUNTIFS(Backlog!$C$2:$C$350,$A25,Backlog!$F$2:$F$350,"Obsolete")-COUNTIFS(Backlog!$C$2:$C$350,$A25,Backlog!$F$2:$F$350,"Later") | H25: =COUNTIFS(Backlog!$C$2:$C$350,$A25,Backlog!$F$2:$F$350,"Done")
A26: Static-to-Dynamic Module Migration | B26: =COUNTIF(Backlog!$C$2:$C$350,$A26) | C26: =COUNTIFS(Backlog!$C$2:$C$350,$A26,Backlog!$G$2:$G$350,"P0") | D26: =COUNTIFS(Backlog!$C$2:$C$350,$A26,Backlog!$G$2:$G$350,"P1") | E26: =COUNTIFS(Backlog!$C$2:$C$350,$A26,Backlog!$G$2:$G$350,"P2") | F26: =COUNTIFS(Backlog!$C$2:$C$350,$A26,Backlog!$G$2:$G$350,"P3") | G26: =B26-H26-COUNTIFS(Backlog!$C$2:$C$350,$A26,Backlog!$F$2:$F$350,"Cancelled")-COUNTIFS(Backlog!$C$2:$C$350,$A26,Backlog!$F$2:$F$350,"Obsolete")-COUNTIFS(Backlog!$C$2:$C$350,$A26,Backlog!$F$2:$F$350,"Later") | H26: =COUNTIFS(Backlog!$C$2:$C$350,$A26,Backlog!$F$2:$F$350,"Done")
A27: Licensing & Protection | B27: =COUNTIF(Backlog!$C$2:$C$350,$A27) | C27: =COUNTIFS(Backlog!$C$2:$C$350,$A27,Backlog!$G$2:$G$350,"P0") | D27: =COUNTIFS(Backlog!$C$2:$C$350,$A27,Backlog!$G$2:$G$350,"P1") | E27: =COUNTIFS(Backlog!$C$2:$C$350,$A27,Backlog!$G$2:$G$350,"P2") | F27: =COUNTIFS(Backlog!$C$2:$C$350,$A27,Backlog!$G$2:$G$350,"P3") | G27: =B27-H27-COUNTIFS(Backlog!$C$2:$C$350,$A27,Backlog!$F$2:$F$350,"Cancelled")-COUNTIFS(Backlog!$C$2:$C$350,$A27,Backlog!$F$2:$F$350,"Obsolete")-COUNTIFS(Backlog!$C$2:$C$350,$A27,Backlog!$F$2:$F$350,"Later") | H27: =COUNTIFS(Backlog!$C$2:$C$350,$A27,Backlog!$F$2:$F$350,"Done")
A28: Company, Brand & Commercial Packaging | B28: =COUNTIF(Backlog!$C$2:$C$350,$A28) | C28: =COUNTIFS(Backlog!$C$2:$C$350,$A28,Backlog!$G$2:$G$350,"P0") | D28: =COUNTIFS(Backlog!$C$2:$C$350,$A28,Backlog!$G$2:$G$350,"P1") | E28: =COUNTIFS(Backlog!$C$2:$C$350,$A28,Backlog!$G$2:$G$350,"P2") | F28: =COUNTIFS(Backlog!$C$2:$C$350,$A28,Backlog!$G$2:$G$350,"P3") | G28: =B28-H28-COUNTIFS(Backlog!$C$2:$C$350,$A28,Backlog!$F$2:$F$350,"Cancelled")-COUNTIFS(Backlog!$C$2:$C$350,$A28,Backlog!$F$2:$F$350,"Obsolete")-COUNTIFS(Backlog!$C$2:$C$350,$A28,Backlog!$F$2:$F$350,"Later") | H28: =COUNTIFS(Backlog!$C$2:$C$350,$A28,Backlog!$F$2:$F$350,"Done")
A29: Online Demo | B29: =COUNTIF(Backlog!$C$2:$C$350,$A29) | C29: =COUNTIFS(Backlog!$C$2:$C$350,$A29,Backlog!$G$2:$G$350,"P0") | D29: =COUNTIFS(Backlog!$C$2:$C$350,$A29,Backlog!$G$2:$G$350,"P1") | E29: =COUNTIFS(Backlog!$C$2:$C$350,$A29,Backlog!$G$2:$G$350,"P2") | F29: =COUNTIFS(Backlog!$C$2:$C$350,$A29,Backlog!$G$2:$G$350,"P3") | G29: =B29-H29-COUNTIFS(Backlog!$C$2:$C$350,$A29,Backlog!$F$2:$F$350,"Cancelled")-COUNTIFS(Backlog!$C$2:$C$350,$A29,Backlog!$F$2:$F$350,"Obsolete")-COUNTIFS(Backlog!$C$2:$C$350,$A29,Backlog!$F$2:$F$350,"Later") | H29: =COUNTIFS(Backlog!$C$2:$C$350,$A29,Backlog!$F$2:$F$350,"Done")
A30: Commercial Website | B30: =COUNTIF(Backlog!$C$2:$C$350,$A30) | C30: =COUNTIFS(Backlog!$C$2:$C$350,$A30,Backlog!$G$2:$G$350,"P0") | D30: =COUNTIFS(Backlog!$C$2:$C$350,$A30,Backlog!$G$2:$G$350,"P1") | E30: =COUNTIFS(Backlog!$C$2:$C$350,$A30,Backlog!$G$2:$G$350,"P2") | F30: =COUNTIFS(Backlog!$C$2:$C$350,$A30,Backlog!$G$2:$G$350,"P3") | G30: =B30-H30-COUNTIFS(Backlog!$C$2:$C$350,$A30,Backlog!$F$2:$F$350,"Cancelled")-COUNTIFS(Backlog!$C$2:$C$350,$A30,Backlog!$F$2:$F$350,"Obsolete")-COUNTIFS(Backlog!$C$2:$C$350,$A30,Backlog!$F$2:$F$350,"Later") | H30: =COUNTIFS(Backlog!$C$2:$C$350,$A30,Backlog!$F$2:$F$350,"Done")
A31: Installation, Deployment & Updates | B31: =COUNTIF(Backlog!$C$2:$C$350,$A31) | C31: =COUNTIFS(Backlog!$C$2:$C$350,$A31,Backlog!$G$2:$G$350,"P0") | D31: =COUNTIFS(Backlog!$C$2:$C$350,$A31,Backlog!$G$2:$G$350,"P1") | E31: =COUNTIFS(Backlog!$C$2:$C$350,$A31,Backlog!$G$2:$G$350,"P2") | F31: =COUNTIFS(Backlog!$C$2:$C$350,$A31,Backlog!$G$2:$G$350,"P3") | G31: =B31-H31-COUNTIFS(Backlog!$C$2:$C$350,$A31,Backlog!$F$2:$F$350,"Cancelled")-COUNTIFS(Backlog!$C$2:$C$350,$A31,Backlog!$F$2:$F$350,"Obsolete")-COUNTIFS(Backlog!$C$2:$C$350,$A31,Backlog!$F$2:$F$350,"Later") | H31: =COUNTIFS(Backlog!$C$2:$C$350,$A31,Backlog!$F$2:$F$350,"Done")
... A46: Main Host: Landing & Demo Deployment | B46: =COUNTIF(Backlog!$C$2:$C$350,$A46) | C46: =COUNTIFS(Backlog!$C$2:$C$350,$A46,Backlog!$G$2:$G$350,"P0") | D46: =COUNTIFS(Backlog!$C$2:$C$350,$A46,Backlog!$G$2:$G$350,"P1") | E46: =COUNTIFS(Backlog!$C$2:$C$350,$A46,Backlog!$G$2:$G$350,"P2") | F46: =COUNTIFS(Backlog!$C$2:$C$350,$A46,Backlog!$G$2:$G$350,"P3") | G46: =B46-H46-COUNTIFS(Backlog!$C$2:$C$350,$A46,Backlog!$F$2:$F$350,"Cancelled")-COUNTIFS(Backlog!$C$2:$C$350,$A46,Backlog!$F$2:$F$350,"Obsolete")-COUNTIFS(Backlog!$C$2:$C$350,$A46,Backlog!$F$2:$F$350,"Later") | H46: =COUNTIFS(Backlog!$C$2:$C$350,$A46,Backlog!$F$2:$F$350,"Done")
A48: Group (related tasks decided and planned together)
A49: Group | B49: Total | C49: Done | D49: Later | E49: Remaining | F49: Confirmed by PM
A50: Foundation & decisions | B50: =COUNTIF(Backlog!$R$2:$R$350,$A50) | C50: =COUNTIFS(Backlog!$R$2:$R$350,$A50,Backlog!$F$2:$F$350,"Done") | D50: =COUNTIFS(Backlog!$R$2:$R$350,$A50,Backlog!$F$2:$F$350,"Later") | E50: =B50-C50-D50-COUNTIFS(Backlog!$R$2:$R$350,$A50,Backlog!$F$2:$F$350,"Cancelled")-COUNTIFS(Backlog!$R$2:$R$350,$A50,Backlog!$F$2:$F$350,"Obsolete") | F50: =COUNTIFS(Backlog!$R$2:$R$350,$A50,Backlog!$S$2:$S$350,"Yes")
A51: Dynamic data core | B51: =COUNTIF(Backlog!$R$2:$R$350,$A51) | C51: =COUNTIFS(Backlog!$R$2:$R$350,$A51,Backlog!$F$2:$F$350,"Done") | D51: =COUNTIFS(Backlog!$R$2:$R$350,$A51,Backlog!$F$2:$F$350,"Later") | E51: =B51-C51-D51-COUNTIFS(Backlog!$R$2:$R$350,$A51,Backlog!$F$2:$F$350,"Cancelled")-COUNTIFS(Backlog!$R$2:$R$350,$A51,Backlog!$F$2:$F$350,"Obsolete") | F51: =COUNTIFS(Backlog!$R$2:$R$350,$A51,Backlog!$S$2:$S$350,"Yes")
A52: UI component library | B52: =COUNTIF(Backlog!$R$2:$R$350,$A52) | C52: =COUNTIFS(Backlog!$R$2:$R$350,$A52,Backlog!$F$2:$F$350,"Done") | D52: =COUNTIFS(Backlog!$R$2:$R$350,$A52,Backlog!$F$2:$F$350,"Later") | E52: =B52-C52-D52-COUNTIFS(Backlog!$R$2:$R$350,$A52,Backlog!$F$2:$F$350,"Cancelled")-COUNTIFS(Backlog!$R$2:$R$350,$A52,Backlog!$F$2:$F$350,"Obsolete") | F52: =COUNTIFS(Backlog!$R$2:$R$350,$A52,Backlog!$S$2:$S$350,"Yes")
A53: Form builder | B53: =COUNTIF(Backlog!$R$2:$R$350,$A53) | C53: =COUNTIFS(Backlog!$R$2:$R$350,$A53,Backlog!$F$2:$F$350,"Done") | D53: =COUNTIFS(Backlog!$R$2:$R$350,$A53,Backlog!$F$2:$F$350,"Later") | E53: =B53-C53-D53-COUNTIFS(Backlog!$R$2:$R$350,$A53,Backlog!$F$2:$F$350,"Cancelled")-COUNTIFS(Backlog!$R$2:$R$350,$A53,Backlog!$F$2:$F$350,"Obsolete") | F53: =COUNTIFS(Backlog!$R$2:$R$350,$A53,Backlog!$S$2:$S$350,"Yes")
A54: Module builder | B54: =COUNTIF(Backlog!$R$2:$R$350,$A54) | C54: =COUNTIFS(Backlog!$R$2:$R$350,$A54,Backlog!$F$2:$F$350,"Done") | D54: =COUNTIFS(Backlog!$R$2:$R$350,$A54,Backlog!$F$2:$F$350,"Later") | E54: =B54-C54-D54-COUNTIFS(Backlog!$R$2:$R$350,$A54,Backlog!$F$2:$F$350,"Cancelled")-COUNTIFS(Backlog!$R$2:$R$350,$A54,Backlog!$F$2:$F$350,"Obsolete") | F54: =COUNTIFS(Backlog!$R$2:$R$350,$A54,Backlog!$S$2:$S$350,"Yes")
A55: Workflow studio & BPMS | B55: =COUNTIF(Backlog!$R$2:$R$350,$A55) | C55: =COUNTIFS(Backlog!$R$2:$R$350,$A55,Backlog!$F$2:$F$350,"Done") | D55: =COUNTIFS(Backlog!$R$2:$R$350,$A55,Backlog!$F$2:$F$350,"Later") | E55: =B55-C55-D55-COUNTIFS(Backlog!$R$2:$R$350,$A55,Backlog!$F$2:$F$350,"Cancelled")-COUNTIFS(Backlog!$R$2:$R$350,$A55,Backlog!$F$2:$F$350,"Obsolete") | F55: =COUNTIFS(Backlog!$R$2:$R$350,$A55,Backlog!$S$2:$S$350,"Yes")
A56: Static-to-dynamic migration | B56: =COUNTIF(Backlog!$R$2:$R$350,$A56) | C56: =COUNTIFS(Backlog!$R$2:$R$350,$A56,Backlog!$F$2:$F$350,"Done") | D56: =COUNTIFS(Backlog!$R$2:$R$350,$A56,Backlog!$F$2:$F$350,"Later") | E56: =B56-C56-D56-COUNTIFS(Backlog!$R$2:$R$350,$A56,Backlog!$F$2:$F$350,"Cancelled")-COUNTIFS(Backlog!$R$2:$R$350,$A56,Backlog!$F$2:$F$350,"Obsolete") | F56: =COUNTIFS(Backlog!$R$2:$R$350,$A56,Backlog!$S$2:$S$350,"Yes")
A57: Licensing chain | B57: =COUNTIF(Backlog!$R$2:$R$350,$A57) | C57: =COUNTIFS(Backlog!$R$2:$R$350,$A57,Backlog!$F$2:$F$350,"Done") | D57: =COUNTIFS(Backlog!$R$2:$R$350,$A57,Backlog!$F$2:$F$350,"Later") | E57: =B57-C57-D57-COUNTIFS(Backlog!$R$2:$R$350,$A57,Backlog!$F$2:$F$350,"Cancelled")-COUNTIFS(Backlog!$R$2:$R$350,$A57,Backlog!$F$2:$F$350,"Obsolete") | F57: =COUNTIFS(Backlog!$R$2:$R$350,$A57,Backlog!$S$2:$S$350,"Yes")
A58: Company, brand & legal | B58: =COUNTIF(Backlog!$R$2:$R$350,$A58) | C58: =COUNTIFS(Backlog!$R$2:$R$350,$A58,Backlog!$F$2:$F$350,"Done") | D58: =COUNTIFS(Backlog!$R$2:$R$350,$A58,Backlog!$F$2:$F$350,"Later") | E58: =B58-C58-D58-COUNTIFS(Backlog!$R$2:$R$350,$A58,Backlog!$F$2:$F$350,"Cancelled")-COUNTIFS(Backlog!$R$2:$R$350,$A58,Backlog!$F$2:$F$350,"Obsolete") | F58: =COUNTIFS(Backlog!$R$2:$R$350,$A58,Backlog!$S$2:$S$350,"Yes")
A59: Online demo | B59: =COUNTIF(Backlog!$R$2:$R$350,$A59) | C59: =COUNTIFS(Backlog!$R$2:$R$350,$A59,Backlog!$F$2:$F$350,"Done") | D59: =COUNTIFS(Backlog!$R$2:$R$350,$A59,Backlog!$F$2:$F$350,"Later") | E59: =B59-C59-D59-COUNTIFS(Backlog!$R$2:$R$350,$A59,Backlog!$F$2:$F$350,"Cancelled")-COUNTIFS(Backlog!$R$2:$R$350,$A59,Backlog!$F$2:$F$350,"Obsolete") | F59: =COUNTIFS(Backlog!$R$2:$R$350,$A59,Backlog!$S$2:$S$350,"Yes")
A60: Commercial website | B60: =COUNTIF(Backlog!$R$2:$R$350,$A60) | C60: =COUNTIFS(Backlog!$R$2:$R$350,$A60,Backlog!$F$2:$F$350,"Done") | D60: =COUNTIFS(Backlog!$R$2:$R$350,$A60,Backlog!$F$2:$F$350,"Later") | E60: =B60-C60-D60-COUNTIFS(Backlog!$R$2:$R$350,$A60,Backlog!$F$2:$F$350,"Cancelled")-COUNTIFS(Backlog!$R$2:$R$350,$A60,Backlog!$F$2:$F$350,"Obsolete") | F60: =COUNTIFS(Backlog!$R$2:$R$350,$A60,Backlog!$S$2:$S$350,"Yes")
A61: Install & update | B61: =COUNTIF(Backlog!$R$2:$R$350,$A61) | C61: =COUNTIFS(Backlog!$R$2:$R$350,$A61,Backlog!$F$2:$F$350,"Done") | D61: =COUNTIFS(Backlog!$R$2:$R$350,$A61,Backlog!$F$2:$F$350,"Later") | E61: =B61-C61-D61-COUNTIFS(Backlog!$R$2:$R$350,$A61,Backlog!$F$2:$F$350,"Cancelled")-COUNTIFS(Backlog!$R$2:$R$350,$A61,Backlog!$F$2:$F$350,"Obsolete") | F61: =COUNTIFS(Backlog!$R$2:$R$350,$A61,Backlog!$S$2:$S$350,"Yes")
... A73: Main host: landing & demo deployment | B73: =COUNTIF(Backlog!$R$2:$R$350,$A73) | C73: =COUNTIFS(Backlog!$R$2:$R$350,$A73,Backlog!$F$2:$F$350,"Done") | D73: =COUNTIFS(Backlog!$R$2:$R$350,$A73,Backlog!$F$2:$F$350,"Later") | E73: =B73-C73-D73-COUNTIFS(Backlog!$R$2:$R$350,$A73,Backlog!$F$2:$F$350,"Cancelled")-COUNTIFS(Backlog!$R$2:$R$350,$A73,Backlog!$F$2:$F$350,"Obsolete") | F73: =COUNTIFS(Backlog!$R$2:$R$350,$A73,Backlog!$S$2:$S$350,"Yes")
A75: Confirmed by PM (all rows) | B75: =COUNTIF(Backlog!$S$2:$S$350,"Yes")
A76: P0 rows confirmed by PM | B76: =COUNTIFS(Backlog!$S$2:$S$350,"Yes",Backlog!$G$2:$G$350,"P0")
A77: Open P0 rows not yet confirmed by PM | B77: =COUNTIFS(Backlog!$S$2:$S$350,"No",Backlog!$G$2:$G$350,"P0",Backlog!$F$2:$F$350,"<>Done",Backlog!$F$2:$F$350,"<>Later",Backlog!$F$2:$F$350,"<>Cancelled",Backlog!$F$2:$F$350,"<>Obsolete")
A78: Rows on Hold | B78: =COUNTIF(Backlog!$F$2:$F$350,"Hold")
A80: Remaining P0 tasks (not Done/Later/Cancelled/Obsolete) | B80: =COUNTIFS(Backlog!$G$2:$G$350,"P0",Backlog!$F$2:$F$350,"<>Done",Backlog!$F$2:$F$350,"<>Cancelled",Backlog!$F$2:$F$350,"<>Obsolete",Backlog!$F$2:$F$350,"<>Later")
A81: Remaining 'Sales blocker' tasks | B81: =COUNTIFS(Backlog!$N$2:$N$350,"Sales blocker",Backlog!$F$2:$F$350,"<>Done")
A82: Open decisions (Decision Needed) | B82: =COUNTIFS(Backlog!$E$2:$E$350,"Decision Needed",Backlog!$F$2:$F$350,"<>Done")
